[{"time": 1199368800, "open": 1299.5, "high": 1299.75, "low": 1299.5, "close": 1299.75, "volume": 18}, {"time": 1199368860, "open": 1299.5, "high": 1299.5, "low": 1299.5, "close": 1299.5, "volume": 3}, {"time": 1199368920, "open": 1299.5, "high": 1299.5, "low": 1299.5, "close": 1299.5, "volume": 1}, {"time": 1199368980, "open": 1299.5, "high": 1299.75, "low": 1299.5, "close": 1299.5, "volume": 527}, {"time": 1199369040, "open": 1299.5, "high": 1299.5, "low": 1299.25, "close": 1299.5, "volume": 71}, {"time": 1199369100, "open": 1299.5, "high": 1299.5, "low": 1299.5, "close": 1299.5, "volume": 42}, {"time": 1199369160, "open": 1299.5, "high": 1299.5, "low": 1299.5, "close": 1299.5, "volume": 295}, {"time": 1199369220, "open": 1299.5, "high": 1299.5, "low": 1299.5, "close": 1299.5, "volume": 2}, {"time": 1199369280, "open": 1299.5, "high": 1299.75, "low": 1299.5, "close": 1299.75, "volume": 2}, {"time": 1199369340, "open": 1299.5, "high": 1299.75, "low": 1299.5, "close": 1299.75, "volume": 3}, {"time": 1199369400, "open": 1299.75, "high": 1299.75, "low": 1299.75, "close": 1299.75, "volume": 5}, {"time": 1199369460, "open": 1299.5, "high": 1299.5, "low": 1299.5, "close": 1299.5, "volume": 13}, {"time": 1199369520, "open": 1299.5, "high": 1299.5, "low": 1299.5, "close": 1299.5, "volume": 7}, {"time": 1199369580, "open": 1299.5, "high": 1299.5, "low": 1299.5, "close": 1299.5, "volume": 34}, {"time": 1199369640, "open": 1299.5, "high": 1299.75, "low": 1299.5, "close": 1299.75, "volume": 6}, {"time": 1199369700, "open": 1299.5, "high": 1299.5, "low": 1299.5, "close": 1299.5, "volume": 68}, {"time": 1199369760, "open": 1299.5, "high": 1299.5, "low": 1299.5, "close": 1299.5, "volume": 23}, {"time": 1199369820, "open": 1299.5, "high": 1299.75, "low": 1299.5, "close": 1299.5, "volume": 169}, {"time": 1199369880, "open": 1299.5, "high": 1299.5, "low": 1299.5, "close": 1299.5, "volume": 10}, {"time": 1199369940, "open": 1299.5, "high": 1299.5, "low": 1299.5, "close": 1299.5, "volume": 10}, {"time": 1199370060, "open": 1299.5, "high": 1299.5, "low": 1299.5, "close": 1299.5, "volume": 1}, {"time": 1199370240, "open": 1299.5, "high": 1299.5, "low": 1299.5, "close": 1299.5, "volume": 1}, {"time": 1199370300, "open": 1299.75, "high": 1299.75, "low": 1299.5, "close": 1299.75, "volume": 50}, {"time": 1199370360, "open": 1299.75, "high": 1299.75, "low": 1299.75, "close": 1299.75, "volume": 5}, {"time": 1199370420, "open": 1299.75, "high": 1299.75, "low": 1299.75, "close": 1299.75, "volume": 2}, {"time": 1199370480, "open": 1299.75, "high": 1299.75, "low": 1299.5, "close": 1299.75, "volume": 74}, {"time": 1199370540, "open": 1299.75, "high": 1300.0, "low": 1299.75, "close": 1299.75, "volume": 10}, {"time": 1199370600, "open": 1299.75, "high": 1299.75, "low": 1299.75, "close": 1299.75, "volume": 2}, {"time": 1199370660, "open": 1300.0, "high": 1300.0, "low": 1300.0, "close": 1300.0, "volume": 20}, {"time": 1199370720, "open": 1299.75, "high": 1299.75, "low": 1299.75, "close": 1299.75, "volume": 3}, {"time": 1199370780, "open": 1299.75, "high": 1299.75, "low": 1299.75, "close": 1299.75, "volume": 6}, {"time": 1199370840, "open": 1299.75, "high": 1300.25, "low": 1299.75, "close": 1300.25, "volume": 176}, {"time": 1199370900, "open": 1300.0, "high": 1300.0, "low": 1300.0, "close": 1300.0, "volume": 1}, {"time": 1199370960, "open": 1300.0, "high": 1300.0, "low": 1300.0, "close": 1300.0, "volume": 2}, {"time": 1199371020, "open": 1300.0, "high": 1300.0, "low": 1300.0, "close": 1300.0, "volume": 7}, {"time": 1199371080, "open": 1300.0, "high": 1300.0, "low": 1299.75, "close": 1300.0, "volume": 34}, {"time": 1199371140, "open": 1300.0, "high": 1300.0, "low": 1299.75, "close": 1299.75, "volume": 35}, {"time": 1199371320, "open": 1299.5, "high": 1299.5, "low": 1299.5, "close": 1299.5, "volume": 36}, {"time": 1199371380, "open": 1299.5, "high": 1299.5, "low": 1299.5, "close": 1299.5, "volume": 41}, {"time": 1199371440, "open": 1299.5, "high": 1299.75, "low": 1299.5, "close": 1299.75, "volume": 45}, {"time": 1199371500, "open": 1299.5, "high": 1299.75, "low": 1299.5, "close": 1299.75, "volume": 25}, {"time": 1199371560, "open": 1299.75, "high": 1299.75, "low": 1299.75, "close": 1299.75, "volume": 6}, {"time": 1199371620, "open": 1299.75, "high": 1299.75, "low": 1299.75, "close": 1299.75, "volume": 37}, {"time": 1199371740, "open": 1299.75, "high": 1300.0, "low": 1299.75, "close": 1299.75, "volume": 3}, {"time": 1199371800, "open": 1299.75, "high": 1299.75, "low": 1299.75, "close": 1299.75, "volume": 10}, {"time": 1199372040, "open": 1299.5, "high": 1299.75, "low": 1299.5, "close": 1299.5, "volume": 10}, {"time": 1199372100, "open": 1299.75, "high": 1299.75, "low": 1299.75, "close": 1299.75, "volume": 30}, {"time": 1199372160, "open": 1299.75, "high": 1299.75, "low": 1299.75, "close": 1299.75, "volume": 3}, {"time": 1199372220, "open": 1299.75, "high": 1299.75, "low": 1299.75, "close": 1299.75, "volume": 2}, {"time": 1199372280, "open": 1299.5, "high": 1299.5, "low": 1299.5, "close": 1299.5, "volume": 111}, {"time": 1199372340, "open": 1299.75, "high": 1299.75, "low": 1299.75, "close": 1299.75, "volume": 49}, {"time": 1199372400, "open": 1300.0, "high": 1300.0, "low": 1300.0, "close": 1300.0, "volume": 3}, {"time": 1199372520, "open": 1300.0, "high": 1300.0, "low": 1299.5, "close": 1299.5, "volume": 10}, {"time": 1199372580, "open": 1299.75, "high": 1299.75, "low": 1299.5, "close": 1299.75, "volume": 25}, {"time": 1199372640, "open": 1300.0, "high": 1300.0, "low": 1300.0, "close": 1300.0, "volume": 30}, {"time": 1199372760, "open": 1299.75, "high": 1299.75, "low": 1299.75, "close": 1299.75, "volume": 1}, {"time": 1199372820, "open": 1300.0, "high": 1300.0, "low": 1300.0, "close": 1300.0, "volume": 40}, {"time": 1199372880, "open": 1300.0, "high": 1300.0, "low": 1300.0, "close": 1300.0, "volume": 20}, {"time": 1199372940, "open": 1300.0, "high": 1300.0, "low": 1300.0, "close": 1300.0, "volume": 11}, {"time": 1199373000, "open": 1300.0, "high": 1300.0, "low": 1300.0, "close": 1300.0, "volume": 1}, {"time": 1199373060, "open": 1300.0, "high": 1300.0, "low": 1299.75, "close": 1300.0, "volume": 18}, {"time": 1199373120, "open": 1300.0, "high": 1300.0, "low": 1299.75, "close": 1299.75, "volume": 5}, {"time": 1199373180, "open": 1300.0, "high": 1300.0, "low": 1300.0, "close": 1300.0, "volume": 17}, {"time": 1199373240, "open": 1300.0, "high": 1300.0, "low": 1300.0, "close": 1300.0, "volume": 2}, {"time": 1199373300, "open": 1300.0, "high": 1300.0, "low": 1300.0, "close": 1300.0, "volume": 12}, {"time": 1199373420, "open": 1300.0, "high": 1300.0, "low": 1300.0, "close": 1300.0, "volume": 14}, {"time": 1199373480, "open": 1300.0, "high": 1300.25, "low": 1300.0, "close": 1300.0, "volume": 10}, {"time": 1199373540, "open": 1300.0, "high": 1300.25, "low": 1300.0, "close": 1300.25, "volume": 22}, {"time": 1199373660, "open": 1300.0, "high": 1300.0, "low": 1300.0, "close": 1300.0, "volume": 1}, {"time": 1199373720, "open": 1300.0, "high": 1300.0, "low": 1300.0, "close": 1300.0, "volume": 10}, {"time": 1199373780, "open": 1300.25, "high": 1300.25, "low": 1300.0, "close": 1300.0, "volume": 31}, {"time": 1199373840, "open": 1300.0, "high": 1300.0, "low": 1300.0, "close": 1300.0, "volume": 82}, {"time": 1199373900, "open": 1300.0, "high": 1300.0, "low": 1300.0, "close": 1300.0, "volume": 2}, {"time": 1199373960, "open": 1300.25, "high": 1300.25, "low": 1300.0, "close": 1300.0, "volume": 2}, {"time": 1199374080, "open": 1300.0, "high": 1300.0, "low": 1300.0, "close": 1300.0, "volume": 6}, {"time": 1199374140, "open": 1300.0, "high": 1300.0, "low": 1300.0, "close": 1300.0, "volume": 1}, {"time": 1199374200, "open": 1300.25, "high": 1300.25, "low": 1299.75, "close": 1300.0, "volume": 36}, {"time": 1199374260, "open": 1299.75, "high": 1300.0, "low": 1299.75, "close": 1299.75, "volume": 17}, {"time": 1199374320, "open": 1300.25, "high": 1300.25, "low": 1300.25, "close": 1300.25, "volume": 3}, {"time": 1199374380, "open": 1299.75, "high": 1299.75, "low": 1299.75, "close": 1299.75, "volume": 4}, {"time": 1199374440, "open": 1299.75, "high": 1299.75, "low": 1299.75, "close": 1299.75, "volume": 1}, {"time": 1199374560, "open": 1299.75, "high": 1299.75, "low": 1299.75, "close": 1299.75, "volume": 5}, {"time": 1199374620, "open": 1299.75, "high": 1299.75, "low": 1299.75, "close": 1299.75, "volume": 3}, {"time": 1199374680, "open": 1299.75, "high": 1299.75, "low": 1299.75, "close": 1299.75, "volume": 4}, {"time": 1199374740, "open": 1299.75, "high": 1299.75, "low": 1299.75, "close": 1299.75, "volume": 4}, {"time": 1199374860, "open": 1300.0, "high": 1300.0, "low": 1300.0, "close": 1300.0, "volume": 114}, {"time": 1199374920, "open": 1300.25, "high": 1300.25, "low": 1300.25, "close": 1300.25, "volume": 10}, {"time": 1199374980, "open": 1300.25, "high": 1300.5, "low": 1300.25, "close": 1300.5, "volume": 54}, {"time": 1199375040, "open": 1300.25, "high": 1300.25, "low": 1300.0, "close": 1300.0, "volume": 16}, {"time": 1199375100, "open": 1300.0, "high": 1300.0, "low": 1300.0, "close": 1300.0, "volume": 10}, {"time": 1199375160, "open": 1300.0, "high": 1300.0, "low": 1300.0, "close": 1300.0, "volume": 5}, {"time": 1199375220, "open": 1300.0, "high": 1300.25, "low": 1300.0, "close": 1300.0, "volume": 35}, {"time": 1199375280, "open": 1300.0, "high": 1300.0, "low": 1300.0, "close": 1300.0, "volume": 15}, {"time": 1199375340, "open": 1300.0, "high": 1300.25, "low": 1300.0, "close": 1300.0, "volume": 3}, {"time": 1199375400, "open": 1300.25, "high": 1300.25, "low": 1300.0, "close": 1300.0, "volume": 3}, {"time": 1199375520, "open": 1300.0, "high": 1300.0, "low": 1300.0, "close": 1300.0, "volume": 85}, {"time": 1199375580, "open": 1300.0, "high": 1300.25, "low": 1300.0, "close": 1300.25, "volume": 14}, {"time": 1199375640, "open": 1300.25, "high": 1300.25, "low": 1300.0, "close": 1300.0, "volume": 4}, {"time": 1199375700, "open": 1300.0, "high": 1300.25, "low": 1300.0, "close": 1300.25, "volume": 13}, {"time": 1199375760, "open": 1300.25, "high": 1300.25, "low": 1300.0, "close": 1300.25, "volume": 45}, {"time": 1199375820, "open": 1300.0, "high": 1300.25, "low": 1300.0, "close": 1300.25, "volume": 3}, {"time": 1199375880, "open": 1300.25, "high": 1300.25, "low": 1300.25, "close": 1300.25, "volume": 1}, {"time": 1199375940, "open": 1300.0, "high": 1300.0, "low": 1300.0, "close": 1300.0, "volume": 42}, {"time": 1199376000, "open": 1300.0, "high": 1300.0, "low": 1299.75, "close": 1300.0, "volume": 234}, {"time": 1199376060, "open": 1300.0, "high": 1300.0, "low": 1299.75, "close": 1300.0, "volume": 33}, {"time": 1199376120, "open": 1300.0, "high": 1300.0, "low": 1300.0, "close": 1300.0, "volume": 87}, {"time": 1199376180, "open": 1299.75, "high": 1299.75, "low": 1299.75, "close": 1299.75, "volume": 59}, {"time": 1199376240, "open": 1299.75, "high": 1300.0, "low": 1299.75, "close": 1300.0, "volume": 10}, {"time": 1199376300, "open": 1299.75, "high": 1300.0, "low": 1299.75, "close": 1300.0, "volume": 97}, {"time": 1199376360, "open": 1299.75, "high": 1300.25, "low": 1299.75, "close": 1300.25, "volume": 40}, {"time": 1199376420, "open": 1300.0, "high": 1300.0, "low": 1300.0, "close": 1300.0, "volume": 4}, {"time": 1199376480, "open": 1300.0, "high": 1300.0, "low": 1300.0, "close": 1300.0, "volume": 25}, {"time": 1199376540, "open": 1300.0, "high": 1300.25, "low": 1300.0, "close": 1300.25, "volume": 7}, {"time": 1199376600, "open": 1300.0, "high": 1300.0, "low": 1300.0, "close": 1300.0, "volume": 124}, {"time": 1199376660, "open": 1300.0, "high": 1300.0, "low": 1300.0, "close": 1300.0, "volume": 115}, {"time": 1199376720, "open": 1300.0, "high": 1300.0, "low": 1300.0, "close": 1300.0, "volume": 43}, {"time": 1199376780, "open": 1300.0, "high": 1300.25, "low": 1300.0, "close": 1300.0, "volume": 5}, {"time": 1199376840, "open": 1300.0, "high": 1300.0, "low": 1299.75, "close": 1299.75, "volume": 61}, {"time": 1199376900, "open": 1299.75, "high": 1299.75, "low": 1299.75, "close": 1299.75, "volume": 51}, {"time": 1199377020, "open": 1299.75, "high": 1300.0, "low": 1299.75, "close": 1300.0, "volume": 22}, {"time": 1199377080, "open": 1299.75, "high": 1300.0, "low": 1299.75, "close": 1299.75, "volume": 14}, {"time": 1199377140, "open": 1299.75, "high": 1299.75, "low": 1299.75, "close": 1299.75, "volume": 23}, {"time": 1199377200, "open": 1299.75, "high": 1299.75, "low": 1299.5, "close": 1299.5, "volume": 34}, {"time": 1199377260, "open": 1299.75, "high": 1300.0, "low": 1299.75, "close": 1300.0, "volume": 5}, {"time": 1199377320, "open": 1299.5, "high": 1299.5, "low": 1299.0, "close": 1299.5, "volume": 418}, {"time": 1199377380, "open": 1299.5, "high": 1299.75, "low": 1298.5, "close": 1299.25, "volume": 467}, {"time": 1199377440, "open": 1299.25, "high": 1299.25, "low": 1299.0, "close": 1299.25, "volume": 37}, {"time": 1199377500, "open": 1299.25, "high": 1299.25, "low": 1299.25, "close": 1299.25, "volume": 17}, {"time": 1199377560, "open": 1299.25, "high": 1299.25, "low": 1299.25, "close": 1299.25, "volume": 12}, {"time": 1199377620, "open": 1299.25, "high": 1299.25, "low": 1299.25, "close": 1299.25, "volume": 28}, {"time": 1199377680, "open": 1299.25, "high": 1299.25, "low": 1299.0, "close": 1299.0, "volume": 41}, {"time": 1199377740, "open": 1299.0, "high": 1299.0, "low": 1298.75, "close": 1298.75, "volume": 14}, {"time": 1199377800, "open": 1299.0, "high": 1299.0, "low": 1298.75, "close": 1298.75, "volume": 46}, {"time": 1199377860, "open": 1298.75, "high": 1298.75, "low": 1298.5, "close": 1298.5, "volume": 15}, {"time": 1199377920, "open": 1298.75, "high": 1299.0, "low": 1298.75, "close": 1298.75, "volume": 14}, {"time": 1199377980, "open": 1298.75, "high": 1299.0, "low": 1298.5, "close": 1299.0, "volume": 46}, {"time": 1199378040, "open": 1298.5, "high": 1298.5, "low": 1298.5, "close": 1298.5, "volume": 26}, {"time": 1199378100, "open": 1298.5, "high": 1298.75, "low": 1298.25, "close": 1298.5, "volume": 46}, {"time": 1199378160, "open": 1298.5, "high": 1298.5, "low": 1298.5, "close": 1298.5, "volume": 23}, {"time": 1199378220, "open": 1298.5, "high": 1298.5, "low": 1298.5, "close": 1298.5, "volume": 20}, {"time": 1199378280, "open": 1298.5, "high": 1298.75, "low": 1298.5, "close": 1298.75, "volume": 56}, {"time": 1199378340, "open": 1298.5, "high": 1298.75, "low": 1298.5, "close": 1298.75, "volume": 3}, {"time": 1199378400, "open": 1298.75, "high": 1298.75, "low": 1298.75, "close": 1298.75, "volume": 10}, {"time": 1199378580, "open": 1298.5, "high": 1298.5, "low": 1298.5, "close": 1298.5, "volume": 27}, {"time": 1199378640, "open": 1298.5, "high": 1298.5, "low": 1298.5, "close": 1298.5, "volume": 11}, {"time": 1199378700, "open": 1298.5, "high": 1298.5, "low": 1298.25, "close": 1298.25, "volume": 16}, {"time": 1199378760, "open": 1298.25, "high": 1298.25, "low": 1298.0, "close": 1298.25, "volume": 212}, {"time": 1199378820, "open": 1298.5, "high": 1298.5, "low": 1298.5, "close": 1298.5, "volume": 1}, {"time": 1199378940, "open": 1298.25, "high": 1298.25, "low": 1298.25, "close": 1298.25, "volume": 4}, {"time": 1199379000, "open": 1298.25, "high": 1298.25, "low": 1298.25, "close": 1298.25, "volume": 65}, {"time": 1199379060, "open": 1298.5, "high": 1298.5, "low": 1298.25, "close": 1298.25, "volume": 68}, {"time": 1199379120, "open": 1298.25, "high": 1298.25, "low": 1298.25, "close": 1298.25, "volume": 111}, {"time": 1199379180, "open": 1298.25, "high": 1298.25, "low": 1298.25, "close": 1298.25, "volume": 10}, {"time": 1199379300, "open": 1298.25, "high": 1298.25, "low": 1298.25, "close": 1298.25, "volume": 5}, {"time": 1199379360, "open": 1298.5, "high": 1298.5, "low": 1298.5, "close": 1298.5, "volume": 3}, {"time": 1199379420, "open": 1298.25, "high": 1298.25, "low": 1298.25, "close": 1298.25, "volume": 7}, {"time": 1199379480, "open": 1298.25, "high": 1298.25, "low": 1298.0, "close": 1298.25, "volume": 42}, {"time": 1199379540, "open": 1298.0, "high": 1298.25, "low": 1298.0, "close": 1298.0, "volume": 103}, {"time": 1199379600, "open": 1298.25, "high": 1298.5, "low": 1297.5, "close": 1297.75, "volume": 347}, {"time": 1199379660, "open": 1297.75, "high": 1297.75, "low": 1297.25, "close": 1297.5, "volume": 252}, {"time": 1199379720, "open": 1297.5, "high": 1297.5, "low": 1297.25, "close": 1297.5, "volume": 224}, {"time": 1199379780, "open": 1297.5, "high": 1299.0, "low": 1297.5, "close": 1298.75, "volume": 833}, {"time": 1199379840, "open": 1298.75, "high": 1299.0, "low": 1298.25, "close": 1298.75, "volume": 215}, {"time": 1199379900, "open": 1298.75, "high": 1299.0, "low": 1298.75, "close": 1299.0, "volume": 72}, {"time": 1199379960, "open": 1298.75, "high": 1299.0, "low": 1298.5, "close": 1298.5, "volume": 51}, {"time": 1199380020, "open": 1298.5, "high": 1298.5, "low": 1297.75, "close": 1298.0, "volume": 67}, {"time": 1199380080, "open": 1298.0, "high": 1298.25, "low": 1298.0, "close": 1298.25, "volume": 26}, {"time": 1199380140, "open": 1298.25, "high": 1298.5, "low": 1297.75, "close": 1298.5, "volume": 128}, {"time": 1199380200, "open": 1298.25, "high": 1298.25, "low": 1298.0, "close": 1298.25, "volume": 201}, {"time": 1199380260, "open": 1298.25, "high": 1298.5, "low": 1298.25, "close": 1298.5, "volume": 186}, {"time": 1199380320, "open": 1298.25, "high": 1298.25, "low": 1298.25, "close": 1298.25, "volume": 50}, {"time": 1199380380, "open": 1298.5, "high": 1298.75, "low": 1298.5, "close": 1298.75, "volume": 230}, {"time": 1199380440, "open": 1298.75, "high": 1299.0, "low": 1298.75, "close": 1298.75, "volume": 128}, {"time": 1199380500, "open": 1298.75, "high": 1299.0, "low": 1298.75, "close": 1299.0, "volume": 176}, {"time": 1199380560, "open": 1299.0, "high": 1299.0, "low": 1299.0, "close": 1299.0, "volume": 6}, {"time": 1199380620, "open": 1299.0, "high": 1299.0, "low": 1299.0, "close": 1299.0, "volume": 26}, {"time": 1199380680, "open": 1298.75, "high": 1299.0, "low": 1298.75, "close": 1299.0, "volume": 118}, {"time": 1199380740, "open": 1299.0, "high": 1299.25, "low": 1299.0, "close": 1299.25, "volume": 175}, {"time": 1199380800, "open": 1299.0, "high": 1299.25, "low": 1299.0, "close": 1299.25, "volume": 72}, {"time": 1199380860, "open": 1299.0, "high": 1299.0, "low": 1298.75, "close": 1298.75, "volume": 304}, {"time": 1199380920, "open": 1298.75, "high": 1298.75, "low": 1298.5, "close": 1298.75, "volume": 275}, {"time": 1199380980, "open": 1299.0, "high": 1299.25, "low": 1298.75, "close": 1299.0, "volume": 199}, {"time": 1199381040, "open": 1299.0, "high": 1299.25, "low": 1298.25, "close": 1298.5, "volume": 962}, {"time": 1199381100, "open": 1298.5, "high": 1298.75, "low": 1297.5, "close": 1297.5, "volume": 753}, {"time": 1199381160, "open": 1297.5, "high": 1298.25, "low": 1297.5, "close": 1298.25, "volume": 359}, {"time": 1199381220, "open": 1298.25, "high": 1298.5, "low": 1298.25, "close": 1298.5, "volume": 68}, {"time": 1199381280, "open": 1298.25, "high": 1298.25, "low": 1298.25, "close": 1298.25, "volume": 46}, {"time": 1199381340, "open": 1298.25, "high": 1298.25, "low": 1298.25, "close": 1298.25, "volume": 19}, {"time": 1199381400, "open": 1298.25, "high": 1298.5, "low": 1298.25, "close": 1298.5, "volume": 108}, {"time": 1199381460, "open": 1298.5, "high": 1298.5, "low": 1298.25, "close": 1298.25, "volume": 11}, {"time": 1199381520, "open": 1298.5, "high": 1298.5, "low": 1298.0, "close": 1298.25, "volume": 145}, {"time": 1199381580, "open": 1298.25, "high": 1298.25, "low": 1298.0, "close": 1298.0, "volume": 14}, {"time": 1199381640, "open": 1298.25, "high": 1298.5, "low": 1298.25, "close": 1298.5, "volume": 369}, {"time": 1199381700, "open": 1298.25, "high": 1298.75, "low": 1298.25, "close": 1298.25, "volume": 123}, {"time": 1199381760, "open": 1298.25, "high": 1298.5, "low": 1298.25, "close": 1298.5, "volume": 3}, {"time": 1199381820, "open": 1298.25, "high": 1298.5, "low": 1298.25, "close": 1298.5, "volume": 7}, {"time": 1199381880, "open": 1298.5, "high": 1298.75, "low": 1298.5, "close": 1298.75, "volume": 106}, {"time": 1199381940, "open": 1298.75, "high": 1298.75, "low": 1298.75, "close": 1298.75, "volume": 197}, {"time": 1199382000, "open": 1298.75, "high": 1298.75, "low": 1298.5, "close": 1298.5, "volume": 114}, {"time": 1199382060, "open": 1298.5, "high": 1298.5, "low": 1298.5, "close": 1298.5, "volume": 36}, {"time": 1199382120, "open": 1298.5, "high": 1298.5, "low": 1298.5, "close": 1298.5, "volume": 8}, {"time": 1199382180, "open": 1298.5, "high": 1298.5, "low": 1298.5, "close": 1298.5, "volume": 121}, {"time": 1199382240, "open": 1298.75, "high": 1299.0, "low": 1298.75, "close": 1298.75, "volume": 131}, {"time": 1199382300, "open": 1298.75, "high": 1298.75, "low": 1298.75, "close": 1298.75, "volume": 4}, {"time": 1199382360, "open": 1298.75, "high": 1298.75, "low": 1298.5, "close": 1298.5, "volume": 240}, {"time": 1199382420, "open": 1298.25, "high": 1298.5, "low": 1298.25, "close": 1298.25, "volume": 19}, {"time": 1199382480, "open": 1298.5, "high": 1298.5, "low": 1298.5, "close": 1298.5, "volume": 99}, {"time": 1199382540, "open": 1298.75, "high": 1298.75, "low": 1298.5, "close": 1298.75, "volume": 42}, {"time": 1199382600, "open": 1298.5, "high": 1298.75, "low": 1298.5, "close": 1298.5, "volume": 88}, {"time": 1199382660, "open": 1298.5, "high": 1298.75, "low": 1298.5, "close": 1298.75, "volume": 7}, {"time": 1199382720, "open": 1298.5, "high": 1298.5, "low": 1298.5, "close": 1298.5, "volume": 44}, {"time": 1199382780, "open": 1298.5, "high": 1298.75, "low": 1298.5, "close": 1298.5, "volume": 209}, {"time": 1199382840, "open": 1298.5, "high": 1298.75, "low": 1298.5, "close": 1298.75, "volume": 30}, {"time": 1199382900, "open": 1298.5, "high": 1298.5, "low": 1298.5, "close": 1298.5, "volume": 53}, {"time": 1199382960, "open": 1298.5, "high": 1298.5, "low": 1298.5, "close": 1298.5, "volume": 51}, {"time": 1199383020, "open": 1298.25, "high": 1298.25, "low": 1298.25, "close": 1298.25, "volume": 1}, {"time": 1199383080, "open": 1298.5, "high": 1298.75, "low": 1298.5, "close": 1298.75, "volume": 149}, {"time": 1199383140, "open": 1298.5, "high": 1298.5, "low": 1298.5, "close": 1298.5, "volume": 5}, {"time": 1199383200, "open": 1298.5, "high": 1298.75, "low": 1298.5, "close": 1298.75, "volume": 9}, {"time": 1199383260, "open": 1298.75, "high": 1298.75, "low": 1298.75, "close": 1298.75, "volume": 1}, {"time": 1199383320, "open": 1298.5, "high": 1298.5, "low": 1298.5, "close": 1298.5, "volume": 5}, {"time": 1199383380, "open": 1298.5, "high": 1298.75, "low": 1298.5, "close": 1298.75, "volume": 2}, {"time": 1199383440, "open": 1298.75, "high": 1298.75, "low": 1298.5, "close": 1298.5, "volume": 18}, {"time": 1199383500, "open": 1298.75, "high": 1298.75, "low": 1298.5, "close": 1298.5, "volume": 9}, {"time": 1199383560, "open": 1298.5, "high": 1298.75, "low": 1298.5, "close": 1298.75, "volume": 10}, {"time": 1199383680, "open": 1298.5, "high": 1298.5, "low": 1298.5, "close": 1298.5, "volume": 22}, {"time": 1199383740, "open": 1298.5, "high": 1298.5, "low": 1298.5, "close": 1298.5, "volume": 63}, {"time": 1199383860, "open": 1298.25, "high": 1298.25, "low": 1298.25, "close": 1298.25, "volume": 39}, {"time": 1199383920, "open": 1298.5, "high": 1298.5, "low": 1298.5, "close": 1298.5, "volume": 163}, {"time": 1199383980, "open": 1298.75, "high": 1298.75, "low": 1298.75, "close": 1298.75, "volume": 7}, {"time": 1199384040, "open": 1298.5, "high": 1298.75, "low": 1298.5, "close": 1298.75, "volume": 71}, {"time": 1199384100, "open": 1298.75, "high": 1298.75, "low": 1298.75, "close": 1298.75, "volume": 121}, {"time": 1199384160, "open": 1298.5, "high": 1298.5, "low": 1298.5, "close": 1298.5, "volume": 99}, {"time": 1199384220, "open": 1298.75, "high": 1298.75, "low": 1298.5, "close": 1298.75, "volume": 52}, {"time": 1199384340, "open": 1298.5, "high": 1298.5, "low": 1298.5, "close": 1298.5, "volume": 25}, {"time": 1199384400, "open": 1298.5, "high": 1298.5, "low": 1298.5, "close": 1298.5, "volume": 11}, {"time": 1199384460, "open": 1298.75, "high": 1298.75, "low": 1298.75, "close": 1298.75, "volume": 110}, {"time": 1199384520, "open": 1298.5, "high": 1298.5, "low": 1298.5, "close": 1298.5, "volume": 6}, {"time": 1199384580, "open": 1298.75, "high": 1299.5, "low": 1298.75, "close": 1299.25, "volume": 523}, {"time": 1199384640, "open": 1299.5, "high": 1299.75, "low": 1299.5, "close": 1299.75, "volume": 242}, {"time": 1199384700, "open": 1299.5, "high": 1299.5, "low": 1299.5, "close": 1299.5, "volume": 85}, {"time": 1199384760, "open": 1299.5, "high": 1300.0, "low": 1299.5, "close": 1300.0, "volume": 171}, {"time": 1199384820, "open": 1300.0, "high": 1300.0, "low": 1299.5, "close": 1299.75, "volume": 220}, {"time": 1199384880, "open": 1299.75, "high": 1299.75, "low": 1299.75, "close": 1299.75, "volume": 36}, {"time": 1199384940, "open": 1299.75, "high": 1300.0, "low": 1299.75, "close": 1299.75, "volume": 52}, {"time": 1199385000, "open": 1299.75, "high": 1300.0, "low": 1299.75, "close": 1299.75, "volume": 188}, {"time": 1199385060, "open": 1299.75, "high": 1300.25, "low": 1299.75, "close": 1299.75, "volume": 229}, {"time": 1199385120, "open": 1300.0, "high": 1300.0, "low": 1299.5, "close": 1299.5, "volume": 104}, {"time": 1199385180, "open": 1299.5, "high": 1299.75, "low": 1299.5, "close": 1299.5, "volume": 38}, {"time": 1199385240, "open": 1299.5, "high": 1299.5, "low": 1299.25, "close": 1299.25, "volume": 547}, {"time": 1199385300, "open": 1299.25, "high": 1300.25, "low": 1299.0, "close": 1300.25, "volume": 1471}, {"time": 1199385360, "open": 1300.0, "high": 1300.5, "low": 1300.0, "close": 1300.25, "volume": 93}, {"time": 1199385420, "open": 1300.0, "high": 1300.25, "low": 1300.0, "close": 1300.0, "volume": 114}, {"time": 1199385480, "open": 1300.25, "high": 1300.5, "low": 1300.25, "close": 1300.25, "volume": 64}, {"time": 1199385540, "open": 1300.25, "high": 1300.25, "low": 1299.75, "close": 1299.75, "volume": 72}, {"time": 1199385600, "open": 1300.0, "high": 1300.0, "low": 1300.0, "close": 1300.0, "volume": 42}, {"time": 1199385660, "open": 1299.75, "high": 1299.75, "low": 1299.75, "close": 1299.75, "volume": 3}, {"time": 1199385720, "open": 1299.75, "high": 1300.0, "low": 1299.75, "close": 1300.0, "volume": 51}, {"time": 1199385780, "open": 1300.0, "high": 1300.0, "low": 1299.25, "close": 1299.25, "volume": 187}, {"time": 1199385840, "open": 1299.0, "high": 1299.25, "low": 1299.0, "close": 1299.25, "volume": 88}, {"time": 1199385900, "open": 1299.5, "high": 1300.0, "low": 1299.5, "close": 1300.0, "volume": 69}, {"time": 1199385960, "open": 1299.75, "high": 1299.75, "low": 1299.25, "close": 1299.5, "volume": 197}, {"time": 1199386020, "open": 1299.5, "high": 1300.0, "low": 1299.5, "close": 1300.0, "volume": 128}, {"time": 1199386080, "open": 1300.0, "high": 1300.0, "low": 1299.75, "close": 1300.0, "volume": 84}, {"time": 1199386140, "open": 1300.0, "high": 1300.0, "low": 1299.5, "close": 1299.75, "volume": 539}, {"time": 1199386200, "open": 1299.5, "high": 1300.0, "low": 1299.5, "close": 1299.75, "volume": 117}, {"time": 1199386260, "open": 1299.5, "high": 1299.75, "low": 1299.5, "close": 1299.75, "volume": 122}, {"time": 1199386320, "open": 1299.75, "high": 1299.75, "low": 1299.5, "close": 1299.5, "volume": 11}, {"time": 1199386380, "open": 1299.5, "high": 1299.5, "low": 1299.5, "close": 1299.5, "volume": 1}, {"time": 1199386440, "open": 1299.75, "high": 1299.75, "low": 1299.5, "close": 1299.5, "volume": 54}, {"time": 1199386500, "open": 1299.5, "high": 1299.5, "low": 1299.5, "close": 1299.5, "volume": 96}, {"time": 1199386560, "open": 1299.5, "high": 1300.0, "low": 1299.5, "close": 1299.75, "volume": 165}, {"time": 1199386620, "open": 1299.75, "high": 1299.75, "low": 1299.75, "close": 1299.75, "volume": 1}, {"time": 1199386680, "open": 1300.0, "high": 1300.0, "low": 1299.5, "close": 1299.5, "volume": 51}, {"time": 1199386740, "open": 1299.75, "high": 1299.75, "low": 1299.75, "close": 1299.75, "volume": 10}, {"time": 1199386800, "open": 1300.0, "high": 1300.0, "low": 1299.75, "close": 1299.75, "volume": 16}, {"time": 1199386860, "open": 1299.75, "high": 1300.0, "low": 1299.75, "close": 1299.75, "volume": 65}, {"time": 1199386920, "open": 1300.0, "high": 1300.0, "low": 1299.75, "close": 1299.75, "volume": 15}, {"time": 1199386980, "open": 1299.75, "high": 1300.0, "low": 1299.75, "close": 1300.0, "volume": 55}, {"time": 1199387040, "open": 1300.0, "high": 1300.25, "low": 1300.0, "close": 1300.0, "volume": 27}, {"time": 1199387100, "open": 1300.25, "high": 1300.25, "low": 1300.0, "close": 1300.25, "volume": 7}, {"time": 1199387160, "open": 1300.0, "high": 1300.25, "low": 1300.0, "close": 1300.25, "volume": 51}, {"time": 1199387220, "open": 1300.25, "high": 1300.25, "low": 1300.0, "close": 1300.25, "volume": 23}, {"time": 1199387280, "open": 1300.25, "high": 1300.25, "low": 1300.0, "close": 1300.0, "volume": 165}, {"time": 1199387340, "open": 1300.25, "high": 1300.25, "low": 1300.0, "close": 1300.0, "volume": 51}, {"time": 1199387400, "open": 1300.0, "high": 1300.25, "low": 1300.0, "close": 1300.25, "volume": 73}, {"time": 1199387460, "open": 1300.25, "high": 1300.25, "low": 1300.25, "close": 1300.25, "volume": 42}, {"time": 1199387520, "open": 1300.25, "high": 1300.25, "low": 1300.25, "close": 1300.25, "volume": 14}, {"time": 1199387580, "open": 1300.25, "high": 1300.25, "low": 1300.25, "close": 1300.25, "volume": 158}, {"time": 1199387640, "open": 1300.25, "high": 1300.25, "low": 1300.25, "close": 1300.25, "volume": 142}, {"time": 1199387700, "open": 1300.25, "high": 1300.5, "low": 1300.25, "close": 1300.25, "volume": 107}, {"time": 1199387760, "open": 1300.25, "high": 1300.25, "low": 1300.25, "close": 1300.25, "volume": 110}, {"time": 1199387820, "open": 1300.25, "high": 1300.25, "low": 1300.25, "close": 1300.25, "volume": 24}, {"time": 1199387880, "open": 1300.5, "high": 1300.75, "low": 1300.25, "close": 1300.75, "volume": 594}, {"time": 1199387940, "open": 1300.75, "high": 1300.75, "low": 1300.5, "close": 1300.5, "volume": 247}, {"time": 1199388000, "open": 1300.5, "high": 1300.75, "low": 1300.5, "close": 1300.5, "volume": 398}, {"time": 1199388060, "open": 1300.75, "high": 1300.75, "low": 1300.5, "close": 1300.5, "volume": 1036}, {"time": 1199388120, "open": 1300.5, "high": 1300.5, "low": 1300.5, "close": 1300.5, "volume": 51}, {"time": 1199388180, "open": 1300.5, "high": 1300.75, "low": 1300.5, "close": 1300.5, "volume": 24}, {"time": 1199388240, "open": 1300.5, "high": 1300.5, "low": 1300.5, "close": 1300.5, "volume": 31}, {"time": 1199388300, "open": 1300.5, "high": 1300.5, "low": 1300.5, "close": 1300.5, "volume": 69}, {"time": 1199388360, "open": 1300.5, "high": 1300.75, "low": 1300.5, "close": 1300.5, "volume": 131}, {"time": 1199388420, "open": 1300.5, "high": 1300.75, "low": 1300.5, "close": 1300.75, "volume": 16}, {"time": 1199388480, "open": 1300.5, "high": 1300.5, "low": 1300.5, "close": 1300.5, "volume": 102}, {"time": 1199388540, "open": 1300.5, "high": 1300.75, "low": 1300.25, "close": 1300.25, "volume": 403}, {"time": 1199388600, "open": 1300.25, "high": 1300.25, "low": 1299.75, "close": 1299.75, "volume": 73}, {"time": 1199388660, "open": 1300.0, "high": 1300.0, "low": 1299.75, "close": 1299.75, "volume": 167}, {"time": 1199388720, "open": 1299.75, "high": 1300.0, "low": 1299.75, "close": 1300.0, "volume": 20}, {"time": 1199388780, "open": 1300.0, "high": 1300.0, "low": 1299.75, "close": 1299.75, "volume": 16}, {"time": 1199388840, "open": 1299.5, "high": 1299.75, "low": 1299.0, "close": 1299.75, "volume": 370}, {"time": 1199388900, "open": 1299.75, "high": 1300.25, "low": 1299.75, "close": 1299.75, "volume": 77}, {"time": 1199388960, "open": 1299.75, "high": 1299.75, "low": 1299.75, "close": 1299.75, "volume": 92}, {"time": 1199389020, "open": 1299.5, "high": 1299.5, "low": 1299.5, "close": 1299.5, "volume": 17}, {"time": 1199389080, "open": 1299.75, "high": 1299.75, "low": 1299.5, "close": 1299.5, "volume": 3}, {"time": 1199389140, "open": 1299.5, "high": 1299.75, "low": 1299.5, "close": 1299.5, "volume": 229}, {"time": 1199389200, "open": 1299.5, "high": 1299.5, "low": 1299.25, "close": 1299.5, "volume": 83}, {"time": 1199389260, "open": 1299.5, "high": 1299.5, "low": 1299.5, "close": 1299.5, "volume": 5}, {"time": 1199389320, "open": 1299.75, "high": 1299.75, "low": 1299.75, "close": 1299.75, "volume": 272}, {"time": 1199389380, "open": 1299.75, "high": 1299.75, "low": 1299.5, "close": 1299.75, "volume": 29}, {"time": 1199389440, "open": 1299.5, "high": 1300.0, "low": 1299.5, "close": 1299.75, "volume": 102}, {"time": 1199389500, "open": 1299.75, "high": 1299.75, "low": 1299.75, "close": 1299.75, "volume": 14}, {"time": 1199389560, "open": 1299.75, "high": 1299.75, "low": 1299.75, "close": 1299.75, "volume": 51}, {"time": 1199389620, "open": 1299.75, "high": 1300.0, "low": 1299.75, "close": 1300.0, "volume": 68}, {"time": 1199389680, "open": 1300.0, "high": 1300.0, "low": 1299.75, "close": 1300.0, "volume": 26}, {"time": 1199389740, "open": 1300.0, "high": 1300.0, "low": 1299.75, "close": 1299.75, "volume": 7}, {"time": 1199389800, "open": 1299.75, "high": 1300.0, "low": 1299.75, "close": 1300.0, "volume": 3}, {"time": 1199389860, "open": 1300.0, "high": 1300.0, "low": 1299.75, "close": 1299.75, "volume": 78}, {"time": 1199389920, "open": 1300.0, "high": 1300.0, "low": 1300.0, "close": 1300.0, "volume": 41}, {"time": 1199389980, "open": 1300.25, "high": 1300.25, "low": 1300.0, "close": 1300.0, "volume": 16}, {"time": 1199390040, "open": 1300.25, "high": 1300.25, "low": 1300.0, "close": 1300.25, "volume": 66}, {"time": 1199390160, "open": 1300.25, "high": 1300.25, "low": 1300.0, "close": 1300.0, "volume": 254}, {"time": 1199390220, "open": 1300.0, "high": 1300.25, "low": 1300.0, "close": 1300.25, "volume": 67}, {"time": 1199390280, "open": 1300.0, "high": 1300.0, "low": 1300.0, "close": 1300.0, "volume": 93}, {"time": 1199390340, "open": 1299.75, "high": 1300.0, "low": 1299.5, "close": 1300.0, "volume": 290}, {"time": 1199390400, "open": 1299.75, "high": 1299.75, "low": 1299.75, "close": 1299.75, "volume": 34}, {"time": 1199390460, "open": 1299.75, "high": 1299.75, "low": 1299.5, "close": 1299.5, "volume": 100}, {"time": 1199390520, "open": 1299.5, "high": 1299.5, "low": 1299.0, "close": 1299.5, "volume": 574}, {"time": 1199390580, "open": 1299.5, "high": 1300.0, "low": 1299.25, "close": 1299.75, "volume": 214}, {"time": 1199390640, "open": 1299.75, "high": 1299.75, "low": 1299.5, "close": 1299.5, "volume": 31}, {"time": 1199390700, "open": 1299.75, "high": 1299.75, "low": 1299.75, "close": 1299.75, "volume": 101}, {"time": 1199390760, "open": 1299.75, "high": 1300.0, "low": 1299.75, "close": 1300.0, "volume": 29}, {"time": 1199390820, "open": 1300.0, "high": 1300.0, "low": 1299.75, "close": 1299.75, "volume": 157}, {"time": 1199390880, "open": 1300.0, "high": 1300.0, "low": 1299.75, "close": 1299.75, "volume": 55}, {"time": 1199390940, "open": 1299.75, "high": 1300.0, "low": 1299.75, "close": 1300.0, "volume": 50}, {"time": 1199391000, "open": 1299.75, "high": 1300.0, "low": 1299.75, "close": 1300.0, "volume": 10}, {"time": 1199391060, "open": 1300.0, "high": 1300.0, "low": 1299.75, "close": 1299.75, "volume": 2}, {"time": 1199391120, "open": 1299.75, "high": 1299.75, "low": 1299.75, "close": 1299.75, "volume": 3}, {"time": 1199391180, "open": 1299.75, "high": 1299.75, "low": 1299.75, "close": 1299.75, "volume": 28}, {"time": 1199391240, "open": 1299.75, "high": 1299.75, "low": 1299.5, "close": 1299.5, "volume": 11}, {"time": 1199391300, "open": 1299.75, "high": 1299.75, "low": 1299.5, "close": 1299.5, "volume": 66}, {"time": 1199391360, "open": 1299.75, "high": 1300.0, "low": 1299.75, "close": 1299.75, "volume": 131}, {"time": 1199391480, "open": 1299.75, "high": 1299.75, "low": 1299.5, "close": 1299.75, "volume": 59}, {"time": 1199391540, "open": 1299.75, "high": 1299.75, "low": 1299.75, "close": 1299.75, "volume": 57}, {"time": 1199391600, "open": 1299.75, "high": 1300.0, "low": 1299.75, "close": 1300.0, "volume": 68}, {"time": 1199391660, "open": 1300.0, "high": 1300.25, "low": 1299.75, "close": 1299.75, "volume": 39}, {"time": 1199391720, "open": 1299.75, "high": 1300.0, "low": 1299.75, "close": 1300.0, "volume": 67}, {"time": 1199391780, "open": 1300.0, "high": 1300.0, "low": 1299.75, "close": 1300.0, "volume": 16}, {"time": 1199391840, "open": 1300.0, "high": 1300.0, "low": 1299.75, "close": 1299.75, "volume": 10}, {"time": 1199391900, "open": 1299.75, "high": 1299.75, "low": 1299.5, "close": 1299.5, "volume": 92}, {"time": 1199391960, "open": 1299.75, "high": 1299.75, "low": 1299.75, "close": 1299.75, "volume": 2}, {"time": 1199392020, "open": 1299.75, "high": 1299.75, "low": 1299.75, "close": 1299.75, "volume": 3}, {"time": 1199392080, "open": 1299.5, "high": 1299.5, "low": 1299.5, "close": 1299.5, "volume": 2}, {"time": 1199392140, "open": 1299.75, "high": 1299.75, "low": 1299.75, "close": 1299.75, "volume": 94}, {"time": 1199392200, "open": 1299.75, "high": 1299.75, "low": 1299.75, "close": 1299.75, "volume": 31}, {"time": 1199392260, "open": 1299.75, "high": 1300.0, "low": 1299.75, "close": 1300.0, "volume": 60}, {"time": 1199392320, "open": 1300.0, "high": 1300.25, "low": 1300.0, "close": 1300.25, "volume": 103}, {"time": 1199392380, "open": 1300.25, "high": 1300.5, "low": 1300.25, "close": 1300.25, "volume": 14}, {"time": 1199392440, "open": 1300.25, "high": 1300.25, "low": 1300.0, "close": 1300.0, "volume": 103}, {"time": 1199392500, "open": 1300.0, "high": 1300.0, "low": 1300.0, "close": 1300.0, "volume": 156}, {"time": 1199392560, "open": 1300.0, "high": 1300.0, "low": 1300.0, "close": 1300.0, "volume": 49}, {"time": 1199392620, "open": 1299.75, "high": 1300.0, "low": 1299.75, "close": 1300.0, "volume": 57}, {"time": 1199392680, "open": 1299.75, "high": 1299.75, "low": 1299.75, "close": 1299.75, "volume": 1}, {"time": 1199392740, "open": 1299.75, "high": 1299.75, "low": 1299.75, "close": 1299.75, "volume": 10}, {"time": 1199392800, "open": 1299.75, "high": 1300.0, "low": 1299.5, "close": 1299.75, "volume": 168}, {"time": 1199392860, "open": 1299.75, "high": 1299.75, "low": 1299.5, "close": 1299.5, "volume": 74}, {"time": 1199392920, "open": 1299.5, "high": 1299.75, "low": 1299.5, "close": 1299.75, "volume": 78}, {"time": 1199392980, "open": 1300.0, "high": 1300.0, "low": 1299.75, "close": 1300.0, "volume": 81}, {"time": 1199393040, "open": 1300.0, "high": 1300.0, "low": 1299.75, "close": 1300.0, "volume": 165}, {"time": 1199393100, "open": 1299.75, "high": 1300.0, "low": 1299.75, "close": 1300.0, "volume": 57}, {"time": 1199393160, "open": 1299.75, "high": 1300.0, "low": 1299.75, "close": 1300.0, "volume": 5}, {"time": 1199393220, "open": 1300.0, "high": 1300.0, "low": 1300.0, "close": 1300.0, "volume": 14}, {"time": 1199393280, "open": 1300.0, "high": 1300.0, "low": 1300.0, "close": 1300.0, "volume": 301}, {"time": 1199393340, "open": 1300.0, "high": 1300.25, "low": 1300.0, "close": 1300.25, "volume": 53}, {"time": 1199393400, "open": 1300.25, "high": 1300.25, "low": 1300.25, "close": 1300.25, "volume": 7}, {"time": 1199393460, "open": 1300.25, "high": 1300.25, "low": 1300.25, "close": 1300.25, "volume": 16}, {"time": 1199393520, "open": 1300.25, "high": 1300.25, "low": 1300.0, "close": 1300.0, "volume": 31}, {"time": 1199393580, "open": 1300.25, "high": 1300.25, "low": 1300.0, "close": 1300.0, "volume": 33}, {"time": 1199393640, "open": 1300.0, "high": 1300.0, "low": 1299.75, "close": 1299.75, "volume": 162}, {"time": 1199393700, "open": 1300.0, "high": 1300.0, "low": 1299.75, "close": 1299.75, "volume": 78}, {"time": 1199393760, "open": 1300.0, "high": 1300.25, "low": 1300.0, "close": 1300.0, "volume": 35}, {"time": 1199393820, "open": 1300.0, "high": 1300.0, "low": 1300.0, "close": 1300.0, "volume": 14}, {"time": 1199393880, "open": 1299.75, "high": 1300.0, "low": 1299.5, "close": 1299.5, "volume": 259}, {"time": 1199393940, "open": 1299.5, "high": 1299.75, "low": 1299.5, "close": 1299.75, "volume": 92}, {"time": 1199394000, "open": 1299.75, "high": 1299.75, "low": 1298.75, "close": 1298.75, "volume": 692}, {"time": 1199394060, "open": 1298.75, "high": 1299.0, "low": 1298.5, "close": 1298.5, "volume": 473}, {"time": 1199394120, "open": 1298.75, "high": 1298.75, "low": 1298.0, "close": 1298.25, "volume": 766}, {"time": 1199394180, "open": 1298.25, "high": 1298.5, "low": 1297.75, "close": 1298.0, "volume": 553}, {"time": 1199394240, "open": 1297.75, "high": 1298.25, "low": 1297.75, "close": 1298.25, "volume": 305}, {"time": 1199394300, "open": 1298.25, "high": 1298.5, "low": 1298.0, "close": 1298.0, "volume": 273}, {"time": 1199394360, "open": 1298.0, "high": 1298.25, "low": 1298.0, "close": 1298.0, "volume": 114}, {"time": 1199394420, "open": 1297.75, "high": 1298.0, "low": 1297.75, "close": 1298.0, "volume": 28}, {"time": 1199394480, "open": 1298.0, "high": 1298.0, "low": 1297.75, "close": 1298.0, "volume": 40}, {"time": 1199394540, "open": 1298.0, "high": 1298.0, "low": 1297.5, "close": 1298.0, "volume": 349}, {"time": 1199394600, "open": 1297.75, "high": 1298.25, "low": 1297.75, "close": 1298.0, "volume": 208}, {"time": 1199394660, "open": 1298.0, "high": 1298.0, "low": 1298.0, "close": 1298.0, "volume": 41}, {"time": 1199394720, "open": 1298.0, "high": 1298.25, "low": 1298.0, "close": 1298.0, "volume": 95}, {"time": 1199394780, "open": 1298.0, "high": 1298.0, "low": 1297.5, "close": 1297.5, "volume": 41}, {"time": 1199394840, "open": 1297.75, "high": 1297.75, "low": 1297.5, "close": 1297.5, "volume": 57}, {"time": 1199394900, "open": 1297.5, "high": 1297.75, "low": 1297.25, "close": 1297.25, "volume": 199}, {"time": 1199394960, "open": 1297.25, "high": 1297.5, "low": 1297.25, "close": 1297.25, "volume": 48}, {"time": 1199395020, "open": 1297.5, "high": 1298.5, "low": 1297.5, "close": 1298.5, "volume": 446}, {"time": 1199395080, "open": 1298.5, "high": 1299.0, "low": 1298.25, "close": 1298.5, "volume": 450}, {"time": 1199395140, "open": 1298.75, "high": 1299.0, "low": 1298.5, "close": 1298.75, "volume": 101}, {"time": 1199395200, "open": 1298.75, "high": 1299.0, "low": 1298.75, "close": 1298.75, "volume": 101}, {"time": 1199395260, "open": 1298.75, "high": 1299.0, "low": 1298.5, "close": 1299.0, "volume": 262}, {"time": 1199395320, "open": 1299.0, "high": 1299.0, "low": 1299.0, "close": 1299.0, "volume": 43}, {"time": 1199395380, "open": 1299.0, "high": 1299.0, "low": 1299.0, "close": 1299.0, "volume": 3}, {"time": 1199395440, "open": 1299.0, "high": 1299.0, "low": 1299.0, "close": 1299.0, "volume": 21}, {"time": 1199395500, "open": 1299.25, "high": 1299.25, "low": 1299.0, "close": 1299.0, "volume": 3}, {"time": 1199395560, "open": 1299.0, "high": 1299.0, "low": 1299.0, "close": 1299.0, "volume": 102}, {"time": 1199395620, "open": 1299.0, "high": 1299.0, "low": 1299.0, "close": 1299.0, "volume": 527}, {"time": 1199395680, "open": 1299.0, "high": 1299.25, "low": 1299.0, "close": 1299.0, "volume": 25}, {"time": 1199395740, "open": 1299.0, "high": 1299.0, "low": 1299.0, "close": 1299.0, "volume": 199}, {"time": 1199395800, "open": 1299.0, "high": 1299.0, "low": 1298.75, "close": 1299.0, "volume": 363}, {"time": 1199395860, "open": 1298.75, "high": 1298.75, "low": 1298.75, "close": 1298.75, "volume": 50}, {"time": 1199395920, "open": 1298.75, "high": 1299.0, "low": 1298.75, "close": 1299.0, "volume": 21}, {"time": 1199395980, "open": 1298.75, "high": 1298.75, "low": 1298.75, "close": 1298.75, "volume": 59}, {"time": 1199396040, "open": 1298.5, "high": 1298.75, "low": 1298.5, "close": 1298.5, "volume": 306}, {"time": 1199396100, "open": 1298.75, "high": 1299.0, "low": 1298.5, "close": 1298.75, "volume": 410}, {"time": 1199396160, "open": 1298.75, "high": 1299.0, "low": 1298.5, "close": 1299.0, "volume": 316}, {"time": 1199396220, "open": 1298.75, "high": 1299.0, "low": 1298.75, "close": 1299.0, "volume": 46}, {"time": 1199396340, "open": 1299.0, "high": 1299.0, "low": 1298.75, "close": 1298.75, "volume": 6}, {"time": 1199396400, "open": 1298.75, "high": 1299.0, "low": 1298.75, "close": 1299.0, "volume": 195}, {"time": 1199396460, "open": 1299.0, "high": 1299.25, "low": 1299.0, "close": 1299.25, "volume": 23}, {"time": 1199396520, "open": 1299.25, "high": 1299.25, "low": 1299.0, "close": 1299.25, "volume": 33}, {"time": 1199396580, "open": 1299.0, "high": 1299.25, "low": 1299.0, "close": 1299.0, "volume": 20}, {"time": 1199396640, "open": 1299.25, "high": 1299.25, "low": 1298.75, "close": 1298.75, "volume": 104}, {"time": 1199396700, "open": 1299.0, "high": 1299.0, "low": 1299.0, "close": 1299.0, "volume": 90}, {"time": 1199396760, "open": 1299.0, "high": 1299.25, "low": 1298.75, "close": 1298.75, "volume": 84}, {"time": 1199396820, "open": 1298.75, "high": 1298.75, "low": 1298.5, "close": 1298.75, "volume": 931}, {"time": 1199396880, "open": 1298.75, "high": 1299.0, "low": 1298.75, "close": 1299.0, "volume": 149}, {"time": 1199396940, "open": 1299.0, "high": 1299.0, "low": 1298.5, "close": 1298.75, "volume": 392}, {"time": 1199397000, "open": 1298.75, "high": 1299.0, "low": 1298.75, "close": 1298.75, "volume": 146}, {"time": 1199397060, "open": 1298.75, "high": 1298.75, "low": 1298.75, "close": 1298.75, "volume": 41}, {"time": 1199397120, "open": 1298.75, "high": 1299.0, "low": 1298.75, "close": 1298.75, "volume": 13}, {"time": 1199397180, "open": 1298.75, "high": 1299.25, "low": 1298.5, "close": 1299.25, "volume": 324}, {"time": 1199397240, "open": 1299.25, "high": 1299.25, "low": 1299.0, "close": 1299.0, "volume": 9}, {"time": 1199397300, "open": 1299.0, "high": 1299.0, "low": 1298.75, "close": 1298.75, "volume": 68}, {"time": 1199397360, "open": 1298.75, "high": 1298.75, "low": 1298.5, "close": 1298.5, "volume": 40}, {"time": 1199397420, "open": 1298.5, "high": 1298.75, "low": 1298.5, "close": 1298.75, "volume": 374}, {"time": 1199397480, "open": 1298.75, "high": 1299.0, "low": 1298.5, "close": 1298.75, "volume": 98}, {"time": 1199397540, "open": 1298.75, "high": 1299.0, "low": 1298.75, "close": 1299.0, "volume": 264}, {"time": 1199397600, "open": 1299.25, "high": 1299.5, "low": 1298.75, "close": 1299.25, "volume": 577}, {"time": 1199397660, "open": 1299.25, "high": 1300.0, "low": 1299.25, "close": 1299.5, "volume": 1077}, {"time": 1199397720, "open": 1299.5, "high": 1299.75, "low": 1299.5, "close": 1299.5, "volume": 136}, {"time": 1199397780, "open": 1299.75, "high": 1300.0, "low": 1299.5, "close": 1300.0, "volume": 292}, {"time": 1199397840, "open": 1299.75, "high": 1300.25, "low": 1299.75, "close": 1299.75, "volume": 343}, {"time": 1199397900, "open": 1299.75, "high": 1300.0, "low": 1299.5, "close": 1299.75, "volume": 324}, {"time": 1199397960, "open": 1299.5, "high": 1299.5, "low": 1299.25, "close": 1299.5, "volume": 688}, {"time": 1199398020, "open": 1299.5, "high": 1299.5, "low": 1299.0, "close": 1299.5, "volume": 890}, {"time": 1199398080, "open": 1299.25, "high": 1299.75, "low": 1299.25, "close": 1299.5, "volume": 440}, {"time": 1199398140, "open": 1299.25, "high": 1299.25, "low": 1299.0, "close": 1299.25, "volume": 160}, {"time": 1199398200, "open": 1299.25, "high": 1299.75, "low": 1299.25, "close": 1299.75, "volume": 468}, {"time": 1199398260, "open": 1299.75, "high": 1299.75, "low": 1299.25, "close": 1299.5, "volume": 330}, {"time": 1199398320, "open": 1299.5, "high": 1299.75, "low": 1299.5, "close": 1299.75, "volume": 299}, {"time": 1199398380, "open": 1299.75, "high": 1299.75, "low": 1296.75, "close": 1297.75, "volume": 3887}, {"time": 1199398440, "open": 1297.75, "high": 1298.5, "low": 1297.5, "close": 1298.25, "volume": 2322}, {"time": 1199398500, "open": 1298.25, "high": 1298.5, "low": 1298.0, "close": 1298.25, "volume": 1222}, {"time": 1199398560, "open": 1298.25, "high": 1298.5, "low": 1298.0, "close": 1298.0, "volume": 288}, {"time": 1199398620, "open": 1298.0, "high": 1298.5, "low": 1298.0, "close": 1298.5, "volume": 621}, {"time": 1199398680, "open": 1298.5, "high": 1300.75, "low": 1298.25, "close": 1298.75, "volume": 2166}, {"time": 1199398740, "open": 1299.0, "high": 1299.25, "low": 1298.25, "close": 1298.25, "volume": 1131}, {"time": 1199398800, "open": 1298.5, "high": 1299.0, "low": 1298.25, "close": 1298.5, "volume": 566}, {"time": 1199398860, "open": 1298.75, "high": 1298.75, "low": 1298.25, "close": 1298.5, "volume": 651}, {"time": 1199398920, "open": 1298.5, "high": 1298.75, "low": 1298.25, "close": 1298.5, "volume": 671}, {"time": 1199398980, "open": 1298.25, "high": 1298.75, "low": 1298.0, "close": 1298.25, "volume": 502}, {"time": 1199399040, "open": 1298.0, "high": 1298.5, "low": 1297.25, "close": 1297.5, "volume": 1475}, {"time": 1199399100, "open": 1297.25, "high": 1298.5, "low": 1296.25, "close": 1298.0, "volume": 3963}, {"time": 1199399160, "open": 1298.25, "high": 1299.25, "low": 1298.0, "close": 1298.75, "volume": 2537}, {"time": 1199399220, "open": 1298.75, "high": 1299.75, "low": 1298.5, "close": 1299.0, "volume": 2110}, {"time": 1199399280, "open": 1299.0, "high": 1299.5, "low": 1298.75, "close": 1299.25, "volume": 658}, {"time": 1199399340, "open": 1299.5, "high": 1300.25, "low": 1298.75, "close": 1299.5, "volume": 1543}, {"time": 1199399400, "open": 1299.25, "high": 1299.25, "low": 1285.5, "close": 1285.5, "volume": 27574}, {"time": 1199399460, "open": 1285.75, "high": 1287.5, "low": 1284.75, "close": 1287.25, "volume": 9880}, {"time": 1199399520, "open": 1287.25, "high": 1287.5, "low": 1283.5, "close": 1284.0, "volume": 8632}, {"time": 1199399580, "open": 1283.75, "high": 1284.5, "low": 1282.5, "close": 1283.25, "volume": 11041}, {"time": 1199399640, "open": 1283.25, "high": 1285.5, "low": 1282.75, "close": 1284.5, "volume": 7236}, {"time": 1199399700, "open": 1284.25, "high": 1285.75, "low": 1283.75, "close": 1284.25, "volume": 6559}, {"time": 1199399760, "open": 1284.25, "high": 1284.5, "low": 1283.0, "close": 1283.25, "volume": 4516}, {"time": 1199399820, "open": 1283.25, "high": 1284.25, "low": 1282.5, "close": 1282.75, "volume": 5038}, {"time": 1199399880, "open": 1282.75, "high": 1284.0, "low": 1282.5, "close": 1283.75, "volume": 3595}, {"time": 1199399940, "open": 1283.5, "high": 1284.0, "low": 1283.0, "close": 1283.25, "volume": 2119}, {"time": 1199400000, "open": 1283.25, "high": 1283.75, "low": 1283.0, "close": 1283.0, "volume": 1607}, {"time": 1199400060, "open": 1283.0, "high": 1283.75, "low": 1282.75, "close": 1283.0, "volume": 2598}, {"time": 1199400120, "open": 1283.0, "high": 1283.75, "low": 1282.75, "close": 1283.5, "volume": 2160}, {"time": 1199400180, "open": 1283.75, "high": 1284.0, "low": 1283.25, "close": 1283.75, "volume": 1924}, {"time": 1199400240, "open": 1283.75, "high": 1284.25, "low": 1283.0, "close": 1283.0, "volume": 2217}, {"time": 1199400300, "open": 1283.0, "high": 1283.5, "low": 1281.75, "close": 1281.75, "volume": 3937}, {"time": 1199400360, "open": 1281.75, "high": 1282.5, "low": 1281.25, "close": 1282.25, "volume": 4621}, {"time": 1199400420, "open": 1282.25, "high": 1283.0, "low": 1281.75, "close": 1283.0, "volume": 2373}, {"time": 1199400480, "open": 1283.0, "high": 1283.5, "low": 1282.75, "close": 1283.0, "volume": 1789}, {"time": 1199400540, "open": 1283.0, "high": 1283.25, "low": 1282.5, "close": 1283.0, "volume": 1072}, {"time": 1199400600, "open": 1283.0, "high": 1283.25, "low": 1282.5, "close": 1283.0, "volume": 608}, {"time": 1199400660, "open": 1282.75, "high": 1283.0, "low": 1282.0, "close": 1282.0, "volume": 1344}, {"time": 1199400720, "open": 1282.0, "high": 1282.5, "low": 1280.75, "close": 1281.0, "volume": 2629}, {"time": 1199400780, "open": 1281.0, "high": 1282.0, "low": 1280.75, "close": 1281.0, "volume": 2574}, {"time": 1199400840, "open": 1281.25, "high": 1281.75, "low": 1280.5, "close": 1281.0, "volume": 1449}, {"time": 1199400900, "open": 1281.0, "high": 1281.25, "low": 1280.5, "close": 1280.75, "volume": 1239}, {"time": 1199400960, "open": 1280.5, "high": 1280.75, "low": 1279.75, "close": 1280.0, "volume": 4231}, {"time": 1199401020, "open": 1280.25, "high": 1280.75, "low": 1279.75, "close": 1280.25, "volume": 2747}, {"time": 1199401080, "open": 1280.25, "high": 1281.25, "low": 1280.25, "close": 1281.0, "volume": 2452}, {"time": 1199401140, "open": 1281.0, "high": 1281.25, "low": 1280.5, "close": 1281.0, "volume": 1431}, {"time": 1199401200, "open": 1281.25, "high": 1281.5, "low": 1281.0, "close": 1281.25, "volume": 1138}, {"time": 1199401260, "open": 1281.0, "high": 1281.0, "low": 1279.75, "close": 1279.75, "volume": 1459}, {"time": 1199401320, "open": 1279.75, "high": 1280.0, "low": 1279.0, "close": 1279.25, "volume": 4520}, {"time": 1199401380, "open": 1279.25, "high": 1280.25, "low": 1279.25, "close": 1279.75, "volume": 2380}, {"time": 1199401440, "open": 1279.75, "high": 1280.0, "low": 1278.0, "close": 1278.75, "volume": 4584}, {"time": 1199401500, "open": 1278.75, "high": 1279.25, "low": 1278.5, "close": 1279.0, "volume": 2779}, {"time": 1199401560, "open": 1279.25, "high": 1279.25, "low": 1278.5, "close": 1278.5, "volume": 1269}, {"time": 1199401620, "open": 1278.75, "high": 1278.75, "low": 1278.0, "close": 1278.0, "volume": 2762}, {"time": 1199401680, "open": 1278.25, "high": 1279.5, "low": 1278.0, "close": 1278.75, "volume": 3610}, {"time": 1199401740, "open": 1278.75, "high": 1279.0, "low": 1278.25, "close": 1279.0, "volume": 1905}, {"time": 1199401800, "open": 1279.0, "high": 1280.0, "low": 1278.75, "close": 1279.5, "volume": 2369}, {"time": 1199401860, "open": 1279.5, "high": 1281.0, "low": 1279.5, "close": 1280.5, "volume": 2932}, {"time": 1199401920, "open": 1280.75, "high": 1281.0, "low": 1280.25, "close": 1280.5, "volume": 894}, {"time": 1199401980, "open": 1280.5, "high": 1280.5, "low": 1280.0, "close": 1280.0, "volume": 641}, {"time": 1199402040, "open": 1280.0, "high": 1280.5, "low": 1279.5, "close": 1280.25, "volume": 1418}, {"time": 1199402100, "open": 1280.25, "high": 1280.25, "low": 1279.75, "close": 1279.75, "volume": 456}, {"time": 1199402160, "open": 1279.75, "high": 1280.0, "low": 1279.5, "close": 1279.75, "volume": 657}, {"time": 1199402220, "open": 1279.5, "high": 1280.0, "low": 1279.5, "close": 1280.0, "volume": 257}, {"time": 1199402280, "open": 1279.75, "high": 1280.0, "low": 1279.5, "close": 1279.5, "volume": 387}, {"time": 1199402340, "open": 1279.5, "high": 1280.0, "low": 1279.25, "close": 1279.75, "volume": 366}, {"time": 1199402400, "open": 1279.75, "high": 1280.0, "low": 1279.5, "close": 1280.0, "volume": 752}, {"time": 1199402460, "open": 1279.75, "high": 1280.75, "low": 1279.75, "close": 1280.75, "volume": 1420}, {"time": 1199402520, "open": 1280.75, "high": 1281.25, "low": 1280.25, "close": 1280.25, "volume": 1094}, {"time": 1199402580, "open": 1280.25, "high": 1280.5, "low": 1280.0, "close": 1280.25, "volume": 315}, {"time": 1199402640, "open": 1280.25, "high": 1280.5, "low": 1279.5, "close": 1279.75, "volume": 1164}, {"time": 1199402700, "open": 1279.75, "high": 1280.25, "low": 1279.5, "close": 1280.0, "volume": 692}, {"time": 1199402760, "open": 1280.0, "high": 1280.0, "low": 1279.5, "close": 1279.5, "volume": 327}, {"time": 1199402820, "open": 1279.5, "high": 1280.25, "low": 1279.5, "close": 1279.75, "volume": 986}, {"time": 1199402880, "open": 1280.0, "high": 1280.5, "low": 1279.75, "close": 1280.0, "volume": 836}, {"time": 1199402940, "open": 1280.25, "high": 1281.0, "low": 1279.75, "close": 1280.5, "volume": 3385}, {"time": 1199403000, "open": 1280.25, "high": 1281.0, "low": 1279.5, "close": 1280.5, "volume": 9537}, {"time": 1199403060, "open": 1280.25, "high": 1280.5, "low": 1279.75, "close": 1280.25, "volume": 5256}, {"time": 1199403120, "open": 1280.25, "high": 1281.25, "low": 1280.0, "close": 1281.0, "volume": 4178}, {"time": 1199403180, "open": 1281.25, "high": 1281.25, "low": 1279.75, "close": 1279.75, "volume": 4940}, {"time": 1199403240, "open": 1279.75, "high": 1280.0, "low": 1277.75, "close": 1278.5, "volume": 8440}, {"time": 1199403300, "open": 1278.5, "high": 1278.5, "low": 1276.75, "close": 1277.0, "volume": 13284}, {"time": 1199403360, "open": 1277.0, "high": 1277.0, "low": 1274.5, "close": 1275.0, "volume": 17987}, {"time": 1199403420, "open": 1275.0, "high": 1276.25, "low": 1274.75, "close": 1275.75, "volume": 12195}, {"time": 1199403480, "open": 1275.75, "high": 1275.75, "low": 1274.25, "close": 1274.5, "volume": 8956}, {"time": 1199403540, "open": 1274.75, "high": 1276.0, "low": 1273.5, "close": 1273.75, "volume": 12208}, {"time": 1199403600, "open": 1274.0, "high": 1275.25, "low": 1273.75, "close": 1275.25, "volume": 5585}, {"time": 1199403660, "open": 1275.25, "high": 1276.5, "low": 1275.0, "close": 1276.25, "volume": 7540}, {"time": 1199403720, "open": 1276.25, "high": 1276.5, "low": 1275.5, "close": 1276.0, "volume": 4877}, {"time": 1199403780, "open": 1276.25, "high": 1277.5, "low": 1276.0, "close": 1277.5, "volume": 7737}, {"time": 1199403840, "open": 1277.5, "high": 1278.0, "low": 1276.75, "close": 1277.25, "volume": 7590}, {"time": 1199403900, "open": 1277.25, "high": 1277.25, "low": 1276.0, "close": 1276.75, "volume": 6144}, {"time": 1199403960, "open": 1276.75, "high": 1277.25, "low": 1276.25, "close": 1277.25, "volume": 3842}, {"time": 1199404020, "open": 1277.25, "high": 1277.5, "low": 1276.0, "close": 1276.0, "volume": 5324}, {"time": 1199404080, "open": 1276.25, "high": 1276.75, "low": 1275.0, "close": 1275.25, "volume": 7345}, {"time": 1199404140, "open": 1275.25, "high": 1276.0, "low": 1274.25, "close": 1275.5, "volume": 9584}, {"time": 1199404200, "open": 1275.25, "high": 1277.0, "low": 1275.0, "close": 1276.5, "volume": 6294}, {"time": 1199404260, "open": 1276.5, "high": 1277.0, "low": 1276.0, "close": 1276.75, "volume": 5918}, {"time": 1199404320, "open": 1277.0, "high": 1277.25, "low": 1276.25, "close": 1276.5, "volume": 3870}, {"time": 1199404380, "open": 1276.5, "high": 1277.0, "low": 1276.25, "close": 1277.0, "volume": 4698}, {"time": 1199404440, "open": 1276.75, "high": 1277.0, "low": 1275.0, "close": 1275.0, "volume": 5323}, {"time": 1199404500, "open": 1275.25, "high": 1275.25, "low": 1273.75, "close": 1274.75, "volume": 7295}, {"time": 1199404560, "open": 1274.75, "high": 1275.0, "low": 1273.75, "close": 1274.5, "volume": 6908}, {"time": 1199404620, "open": 1274.5, "high": 1275.25, "low": 1274.5, "close": 1275.25, "volume": 3473}, {"time": 1199404680, "open": 1275.25, "high": 1276.5, "low": 1275.25, "close": 1276.25, "volume": 4216}, {"time": 1199404740, "open": 1276.5, "high": 1276.5, "low": 1275.75, "close": 1276.5, "volume": 3614}, {"time": 1199404800, "open": 1276.25, "high": 1278.75, "low": 1276.25, "close": 1278.25, "volume": 16699}, {"time": 1199404860, "open": 1278.0, "high": 1278.25, "low": 1275.75, "close": 1277.25, "volume": 13074}, {"time": 1199404920, "open": 1277.0, "high": 1277.5, "low": 1276.5, "close": 1276.5, "volume": 3840}, {"time": 1199404980, "open": 1276.5, "high": 1276.5, "low": 1273.75, "close": 1274.0, "volume": 12776}, {"time": 1199405040, "open": 1273.75, "high": 1276.0, "low": 1273.0, "close": 1275.75, "volume": 14129}, {"time": 1199405100, "open": 1276.0, "high": 1276.5, "low": 1275.0, "close": 1275.75, "volume": 7039}, {"time": 1199405160, "open": 1276.0, "high": 1276.25, "low": 1275.0, "close": 1275.0, "volume": 5107}, {"time": 1199405220, "open": 1274.75, "high": 1276.0, "low": 1274.5, "close": 1275.75, "volume": 3899}, {"time": 1199405280, "open": 1275.75, "high": 1276.5, "low": 1275.5, "close": 1275.75, "volume": 4008}, {"time": 1199405340, "open": 1275.75, "high": 1277.0, "low": 1275.75, "close": 1276.75, "volume": 4146}, {"time": 1199405400, "open": 1276.75, "high": 1277.0, "low": 1275.75, "close": 1276.25, "volume": 2509}, {"time": 1199405460, "open": 1276.25, "high": 1276.25, "low": 1275.0, "close": 1275.75, "volume": 5770}, {"time": 1199405520, "open": 1276.0, "high": 1276.25, "low": 1275.0, "close": 1275.5, "volume": 2197}, {"time": 1199405580, "open": 1275.75, "high": 1275.75, "low": 1273.75, "close": 1274.0, "volume": 5631}, {"time": 1199405640, "open": 1274.0, "high": 1275.25, "low": 1273.5, "close": 1274.75, "volume": 5047}, {"time": 1199405700, "open": 1274.75, "high": 1275.0, "low": 1274.5, "close": 1274.75, "volume": 1671}, {"time": 1199405760, "open": 1275.0, "high": 1275.0, "low": 1273.75, "close": 1274.0, "volume": 3422}, {"time": 1199405820, "open": 1274.0, "high": 1274.75, "low": 1273.5, "close": 1273.5, "volume": 2984}, {"time": 1199405880, "open": 1273.5, "high": 1274.25, "low": 1272.75, "close": 1272.75, "volume": 6336}, {"time": 1199405940, "open": 1272.75, "high": 1273.25, "low": 1271.5, "close": 1271.75, "volume": 10233}, {"time": 1199406000, "open": 1271.75, "high": 1273.0, "low": 1271.5, "close": 1272.5, "volume": 5654}, {"time": 1199406060, "open": 1272.75, "high": 1273.5, "low": 1272.25, "close": 1273.25, "volume": 4741}, {"time": 1199406120, "open": 1273.25, "high": 1273.75, "low": 1273.25, "close": 1273.5, "volume": 2758}, {"time": 1199406180, "open": 1273.25, "high": 1274.0, "low": 1273.0, "close": 1273.0, "volume": 3775}, {"time": 1199406240, "open": 1273.0, "high": 1273.25, "low": 1272.25, "close": 1272.75, "volume": 3585}, {"time": 1199406300, "open": 1273.0, "high": 1273.0, "low": 1271.0, "close": 1272.25, "volume": 8446}, {"time": 1199406360, "open": 1272.25, "high": 1272.5, "low": 1271.5, "close": 1271.5, "volume": 5355}, {"time": 1199406420, "open": 1271.5, "high": 1271.75, "low": 1270.0, "close": 1270.0, "volume": 9273}, {"time": 1199406480, "open": 1270.25, "high": 1271.25, "low": 1270.0, "close": 1270.75, "volume": 6186}, {"time": 1199406540, "open": 1270.75, "high": 1271.0, "low": 1269.5, "close": 1270.75, "volume": 7306}, {"time": 1199406600, "open": 1270.75, "high": 1270.75, "low": 1270.0, "close": 1270.75, "volume": 4021}, {"time": 1199406660, "open": 1270.75, "high": 1271.25, "low": 1269.0, "close": 1269.5, "volume": 6492}, {"time": 1199406720, "open": 1269.5, "high": 1270.5, "low": 1269.0, "close": 1270.0, "volume": 6155}, {"time": 1199406780, "open": 1270.0, "high": 1271.0, "low": 1269.75, "close": 1270.75, "volume": 5289}, {"time": 1199406840, "open": 1270.75, "high": 1271.5, "low": 1270.5, "close": 1271.25, "volume": 4431}, {"time": 1199406900, "open": 1271.25, "high": 1272.25, "low": 1271.0, "close": 1272.0, "volume": 5629}, {"time": 1199406960, "open": 1272.25, "high": 1272.25, "low": 1270.75, "close": 1270.75, "volume": 7229}, {"time": 1199407020, "open": 1270.75, "high": 1271.25, "low": 1270.0, "close": 1270.75, "volume": 5076}, {"time": 1199407080, "open": 1270.5, "high": 1270.75, "low": 1270.0, "close": 1270.25, "volume": 2976}, {"time": 1199407140, "open": 1270.5, "high": 1270.5, "low": 1269.75, "close": 1270.0, "volume": 3115}, {"time": 1199407200, "open": 1270.0, "high": 1270.5, "low": 1270.0, "close": 1270.5, "volume": 2517}, {"time": 1199407260, "open": 1270.5, "high": 1270.75, "low": 1270.0, "close": 1270.5, "volume": 3901}, {"time": 1199407320, "open": 1270.5, "high": 1272.0, "low": 1270.5, "close": 1271.5, "volume": 7466}, {"time": 1199407380, "open": 1271.25, "high": 1271.75, "low": 1271.0, "close": 1271.25, "volume": 1624}, {"time": 1199407440, "open": 1271.25, "high": 1271.5, "low": 1270.0, "close": 1270.75, "volume": 3669}, {"time": 1199407500, "open": 1270.5, "high": 1271.25, "low": 1270.25, "close": 1270.5, "volume": 4152}, {"time": 1199407560, "open": 1270.5, "high": 1270.5, "low": 1267.75, "close": 1268.75, "volume": 14453}, {"time": 1199407620, "open": 1268.5, "high": 1268.75, "low": 1267.5, "close": 1267.5, "volume": 5643}, {"time": 1199407680, "open": 1267.75, "high": 1268.75, "low": 1267.0, "close": 1268.5, "volume": 9261}, {"time": 1199407740, "open": 1268.5, "high": 1269.0, "low": 1267.75, "close": 1268.75, "volume": 5786}, {"time": 1199407800, "open": 1268.75, "high": 1269.0, "low": 1266.75, "close": 1267.0, "volume": 8251}, {"time": 1199407860, "open": 1267.0, "high": 1267.75, "low": 1266.75, "close": 1267.25, "volume": 6764}, {"time": 1199407920, "open": 1267.25, "high": 1268.5, "low": 1267.0, "close": 1268.0, "volume": 5612}, {"time": 1199407980, "open": 1267.75, "high": 1268.25, "low": 1266.75, "close": 1267.75, "volume": 6044}, {"time": 1199408040, "open": 1267.75, "high": 1267.75, "low": 1266.5, "close": 1266.75, "volume": 5441}, {"time": 1199408100, "open": 1266.75, "high": 1267.75, "low": 1266.5, "close": 1266.75, "volume": 5665}, {"time": 1199408160, "open": 1266.75, "high": 1267.25, "low": 1265.75, "close": 1265.75, "volume": 5991}, {"time": 1199408220, "open": 1266.0, "high": 1266.5, "low": 1265.0, "close": 1265.75, "volume": 6818}, {"time": 1199408280, "open": 1266.0, "high": 1266.25, "low": 1265.5, "close": 1266.0, "volume": 3404}, {"time": 1199408340, "open": 1265.75, "high": 1266.25, "low": 1265.5, "close": 1266.0, "volume": 3192}, {"time": 1199408400, "open": 1266.0, "high": 1267.5, "low": 1265.75, "close": 1266.75, "volume": 8040}, {"time": 1199408460, "open": 1267.0, "high": 1267.25, "low": 1266.5, "close": 1267.0, "volume": 3737}, {"time": 1199408520, "open": 1267.0, "high": 1267.25, "low": 1266.5, "close": 1267.0, "volume": 2846}, {"time": 1199408580, "open": 1266.75, "high": 1267.25, "low": 1266.0, "close": 1266.0, "volume": 3841}, {"time": 1199408640, "open": 1266.0, "high": 1266.75, "low": 1265.75, "close": 1266.5, "volume": 2619}, {"time": 1199408700, "open": 1266.25, "high": 1266.5, "low": 1265.75, "close": 1266.25, "volume": 3383}, {"time": 1199408760, "open": 1266.0, "high": 1266.5, "low": 1265.0, "close": 1265.0, "volume": 2648}, {"time": 1199408820, "open": 1265.25, "high": 1265.5, "low": 1263.75, "close": 1264.0, "volume": 9963}, {"time": 1199408880, "open": 1264.0, "high": 1265.0, "low": 1264.0, "close": 1265.0, "volume": 4268}, {"time": 1199408940, "open": 1265.0, "high": 1265.75, "low": 1265.0, "close": 1265.75, "volume": 3760}, {"time": 1199409000, "open": 1265.5, "high": 1266.25, "low": 1264.75, "close": 1265.75, "volume": 6475}, {"time": 1199409060, "open": 1265.75, "high": 1267.0, "low": 1265.5, "close": 1266.75, "volume": 5918}, {"time": 1199409120, "open": 1266.5, "high": 1268.0, "low": 1266.5, "close": 1267.75, "volume": 4471}, {"time": 1199409180, "open": 1268.0, "high": 1268.5, "low": 1267.5, "close": 1268.5, "volume": 5922}, {"time": 1199409240, "open": 1268.25, "high": 1268.5, "low": 1267.75, "close": 1267.75, "volume": 3945}, {"time": 1199409300, "open": 1268.0, "high": 1268.0, "low": 1266.75, "close": 1267.25, "volume": 7212}, {"time": 1199409360, "open": 1267.0, "high": 1267.5, "low": 1266.75, "close": 1267.0, "volume": 1673}, {"time": 1199409420, "open": 1267.0, "high": 1267.25, "low": 1265.75, "close": 1265.75, "volume": 6890}, {"time": 1199409480, "open": 1266.0, "high": 1266.25, "low": 1265.0, "close": 1265.5, "volume": 3430}, {"time": 1199409540, "open": 1265.5, "high": 1266.0, "low": 1265.0, "close": 1265.75, "volume": 2555}, {"time": 1199409600, "open": 1265.75, "high": 1267.25, "low": 1265.75, "close": 1267.0, "volume": 4131}, {"time": 1199409660, "open": 1267.0, "high": 1267.0, "low": 1266.25, "close": 1266.25, "volume": 1997}, {"time": 1199409720, "open": 1266.25, "high": 1267.25, "low": 1265.75, "close": 1267.25, "volume": 3309}, {"time": 1199409780, "open": 1267.25, "high": 1267.75, "low": 1266.5, "close": 1267.75, "volume": 4727}, {"time": 1199409840, "open": 1267.75, "high": 1268.0, "low": 1267.25, "close": 1268.0, "volume": 4105}, {"time": 1199409900, "open": 1268.0, "high": 1270.25, "low": 1268.0, "close": 1270.0, "volume": 13678}, {"time": 1199409960, "open": 1270.0, "high": 1270.25, "low": 1269.0, "close": 1269.25, "volume": 7441}, {"time": 1199410020, "open": 1269.5, "high": 1270.5, "low": 1269.0, "close": 1270.25, "volume": 6726}, {"time": 1199410080, "open": 1270.5, "high": 1271.0, "low": 1270.25, "close": 1270.75, "volume": 8541}, {"time": 1199410140, "open": 1270.75, "high": 1271.0, "low": 1270.25, "close": 1270.5, "volume": 5697}, {"time": 1199410200, "open": 1270.5, "high": 1271.5, "low": 1270.25, "close": 1271.0, "volume": 5992}, {"time": 1199410260, "open": 1271.0, "high": 1271.0, "low": 1270.25, "close": 1270.75, "volume": 3672}, {"time": 1199410320, "open": 1270.75, "high": 1271.0, "low": 1270.25, "close": 1270.75, "volume": 4279}, {"time": 1199410380, "open": 1271.0, "high": 1271.25, "low": 1270.25, "close": 1270.5, "volume": 4072}, {"time": 1199410440, "open": 1270.5, "high": 1271.0, "low": 1270.25, "close": 1270.5, "volume": 3458}, {"time": 1199410500, "open": 1270.5, "high": 1270.75, "low": 1269.25, "close": 1269.5, "volume": 7155}, {"time": 1199410560, "open": 1269.75, "high": 1270.0, "low": 1269.0, "close": 1269.25, "volume": 4202}, {"time": 1199410620, "open": 1269.25, "high": 1269.5, "low": 1268.25, "close": 1268.5, "volume": 5800}, {"time": 1199410680, "open": 1268.25, "high": 1268.75, "low": 1267.75, "close": 1268.5, "volume": 5854}, {"time": 1199410740, "open": 1268.5, "high": 1269.0, "low": 1268.0, "close": 1268.25, "volume": 3820}, {"time": 1199410800, "open": 1268.0, "high": 1268.75, "low": 1267.75, "close": 1268.25, "volume": 2063}, {"time": 1199410860, "open": 1268.25, "high": 1269.0, "low": 1267.75, "close": 1268.0, "volume": 3685}, {"time": 1199410920, "open": 1267.75, "high": 1268.25, "low": 1267.25, "close": 1267.75, "volume": 6208}, {"time": 1199410980, "open": 1267.75, "high": 1268.5, "low": 1267.5, "close": 1268.0, "volume": 3298}, {"time": 1199411040, "open": 1267.75, "high": 1268.5, "low": 1267.75, "close": 1267.75, "volume": 2267}, {"time": 1199411100, "open": 1267.75, "high": 1268.5, "low": 1267.75, "close": 1268.25, "volume": 1886}, {"time": 1199411160, "open": 1268.25, "high": 1268.75, "low": 1267.5, "close": 1267.75, "volume": 3206}, {"time": 1199411220, "open": 1267.75, "high": 1268.5, "low": 1267.75, "close": 1268.25, "volume": 1509}, {"time": 1199411280, "open": 1268.5, "high": 1268.5, "low": 1268.0, "close": 1268.25, "volume": 1199}, {"time": 1199411340, "open": 1268.25, "high": 1268.5, "low": 1267.75, "close": 1268.25, "volume": 1586}, {"time": 1199411400, "open": 1268.25, "high": 1270.0, "low": 1268.25, "close": 1269.5, "volume": 3620}, {"time": 1199411460, "open": 1269.25, "high": 1270.0, "low": 1269.25, "close": 1269.75, "volume": 923}, {"time": 1199411520, "open": 1269.75, "high": 1270.5, "low": 1269.5, "close": 1270.5, "volume": 1717}, {"time": 1199411580, "open": 1270.5, "high": 1270.5, "low": 1268.5, "close": 1269.25, "volume": 3941}, {"time": 1199411640, "open": 1269.0, "high": 1269.75, "low": 1268.5, "close": 1269.75, "volume": 2138}, {"time": 1199411700, "open": 1269.75, "high": 1270.25, "low": 1269.5, "close": 1270.25, "volume": 1577}, {"time": 1199411760, "open": 1270.25, "high": 1270.25, "low": 1269.75, "close": 1270.0, "volume": 757}, {"time": 1199411820, "open": 1270.0, "high": 1270.0, "low": 1269.0, "close": 1269.0, "volume": 1337}, {"time": 1199411880, "open": 1269.0, "high": 1270.0, "low": 1268.75, "close": 1269.0, "volume": 1708}, {"time": 1199411940, "open": 1269.0, "high": 1270.0, "low": 1269.0, "close": 1269.75, "volume": 1364}, {"time": 1199412000, "open": 1270.0, "high": 1271.25, "low": 1269.75, "close": 1270.75, "volume": 6868}, {"time": 1199412060, "open": 1271.0, "high": 1271.5, "low": 1270.75, "close": 1271.0, "volume": 3655}, {"time": 1199412120, "open": 1271.0, "high": 1271.0, "low": 1270.5, "close": 1271.0, "volume": 913}, {"time": 1199412180, "open": 1271.0, "high": 1271.75, "low": 1270.75, "close": 1271.5, "volume": 3265}, {"time": 1199412240, "open": 1271.5, "high": 1271.75, "low": 1271.0, "close": 1271.25, "volume": 3118}, {"time": 1199412300, "open": 1271.0, "high": 1271.75, "low": 1270.75, "close": 1271.75, "volume": 1441}, {"time": 1199412360, "open": 1271.5, "high": 1272.0, "low": 1271.25, "close": 1272.0, "volume": 2130}, {"time": 1199412420, "open": 1271.75, "high": 1272.5, "low": 1271.5, "close": 1271.75, "volume": 4599}, {"time": 1199412480, "open": 1271.75, "high": 1273.5, "low": 1271.75, "close": 1273.25, "volume": 8050}, {"time": 1199412540, "open": 1273.25, "high": 1273.5, "low": 1273.0, "close": 1273.25, "volume": 7641}, {"time": 1199412600, "open": 1273.5, "high": 1273.75, "low": 1272.75, "close": 1273.0, "volume": 4360}, {"time": 1199412660, "open": 1272.75, "high": 1273.0, "low": 1272.5, "close": 1273.0, "volume": 3515}, {"time": 1199412720, "open": 1272.75, "high": 1273.25, "low": 1272.75, "close": 1273.0, "volume": 1264}, {"time": 1199412780, "open": 1273.0, "high": 1273.5, "low": 1273.0, "close": 1273.25, "volume": 1214}, {"time": 1199412840, "open": 1273.5, "high": 1273.75, "low": 1272.75, "close": 1273.0, "volume": 2493}, {"time": 1199412900, "open": 1272.75, "high": 1273.25, "low": 1272.5, "close": 1272.75, "volume": 2920}, {"time": 1199412960, "open": 1272.5, "high": 1272.75, "low": 1272.25, "close": 1272.25, "volume": 2516}, {"time": 1199413020, "open": 1272.25, "high": 1272.5, "low": 1272.0, "close": 1272.0, "volume": 1340}, {"time": 1199413080, "open": 1272.25, "high": 1272.75, "low": 1272.0, "close": 1272.0, "volume": 2505}, {"time": 1199413140, "open": 1272.25, "high": 1272.75, "low": 1272.0, "close": 1272.5, "volume": 1321}, {"time": 1199413200, "open": 1272.5, "high": 1272.5, "low": 1272.0, "close": 1272.0, "volume": 461}, {"time": 1199413260, "open": 1272.0, "high": 1272.0, "low": 1271.0, "close": 1271.0, "volume": 2001}, {"time": 1199413320, "open": 1271.0, "high": 1271.25, "low": 1270.5, "close": 1270.75, "volume": 2979}, {"time": 1199413380, "open": 1270.5, "high": 1271.0, "low": 1270.25, "close": 1270.25, "volume": 1649}, {"time": 1199413440, "open": 1270.5, "high": 1270.5, "low": 1269.0, "close": 1269.5, "volume": 3663}, {"time": 1199413500, "open": 1269.25, "high": 1269.75, "low": 1269.25, "close": 1269.25, "volume": 1494}, {"time": 1199413560, "open": 1269.5, "high": 1269.5, "low": 1268.0, "close": 1268.5, "volume": 3232}, {"time": 1199413620, "open": 1268.25, "high": 1268.5, "low": 1267.75, "close": 1268.25, "volume": 3680}, {"time": 1199413680, "open": 1268.25, "high": 1268.25, "low": 1267.5, "close": 1268.0, "volume": 1794}, {"time": 1199413740, "open": 1268.0, "high": 1268.5, "low": 1267.5, "close": 1268.25, "volume": 2518}, {"time": 1199413800, "open": 1268.25, "high": 1269.25, "low": 1268.0, "close": 1269.0, "volume": 2812}, {"time": 1199413860, "open": 1268.75, "high": 1269.5, "low": 1267.75, "close": 1267.75, "volume": 2719}, {"time": 1199413920, "open": 1267.75, "high": 1268.0, "low": 1267.5, "close": 1268.0, "volume": 1609}, {"time": 1199413980, "open": 1267.75, "high": 1267.75, "low": 1265.75, "close": 1266.5, "volume": 7128}, {"time": 1199414040, "open": 1266.5, "high": 1266.5, "low": 1266.0, "close": 1266.5, "volume": 1985}, {"time": 1199414100, "open": 1266.5, "high": 1267.0, "low": 1265.75, "close": 1267.0, "volume": 3798}, {"time": 1199414160, "open": 1267.0, "high": 1267.5, "low": 1266.5, "close": 1267.0, "volume": 3938}, {"time": 1199414220, "open": 1267.0, "high": 1267.75, "low": 1266.75, "close": 1267.75, "volume": 3526}, {"time": 1199414280, "open": 1267.5, "high": 1267.5, "low": 1266.5, "close": 1266.75, "volume": 2499}, {"time": 1199414340, "open": 1267.0, "high": 1267.0, "low": 1266.0, "close": 1266.0, "volume": 2910}, {"time": 1199414400, "open": 1266.0, "high": 1266.75, "low": 1265.75, "close": 1266.5, "volume": 4021}, {"time": 1199414460, "open": 1266.25, "high": 1267.0, "low": 1266.0, "close": 1267.0, "volume": 2923}, {"time": 1199414520, "open": 1267.0, "high": 1268.0, "low": 1266.75, "close": 1268.0, "volume": 2159}, {"time": 1199414580, "open": 1268.0, "high": 1268.25, "low": 1267.5, "close": 1268.0, "volume": 2278}, {"time": 1199414640, "open": 1268.25, "high": 1268.25, "low": 1267.75, "close": 1267.75, "volume": 798}, {"time": 1199414700, "open": 1267.75, "high": 1268.25, "low": 1267.25, "close": 1267.75, "volume": 1035}, {"time": 1199414760, "open": 1267.75, "high": 1268.75, "low": 1267.5, "close": 1268.75, "volume": 1401}, {"time": 1199414820, "open": 1268.75, "high": 1269.0, "low": 1268.25, "close": 1268.25, "volume": 1528}, {"time": 1199414880, "open": 1268.25, "high": 1269.0, "low": 1268.25, "close": 1269.0, "volume": 1452}, {"time": 1199414940, "open": 1268.75, "high": 1269.75, "low": 1268.75, "close": 1269.5, "volume": 2551}, {"time": 1199415000, "open": 1269.5, "high": 1269.75, "low": 1269.0, "close": 1269.0, "volume": 2457}, {"time": 1199415060, "open": 1269.25, "high": 1269.25, "low": 1268.25, "close": 1268.5, "volume": 1530}, {"time": 1199415120, "open": 1268.5, "high": 1269.0, "low": 1268.25, "close": 1268.25, "volume": 964}, {"time": 1199415180, "open": 1268.5, "high": 1268.75, "low": 1268.0, "close": 1268.5, "volume": 923}, {"time": 1199415240, "open": 1268.25, "high": 1268.75, "low": 1268.0, "close": 1268.0, "volume": 833}, {"time": 1199415300, "open": 1268.0, "high": 1268.25, "low": 1267.75, "close": 1268.0, "volume": 672}, {"time": 1199415360, "open": 1268.25, "high": 1268.75, "low": 1268.25, "close": 1268.5, "volume": 1352}, {"time": 1199415420, "open": 1268.75, "high": 1268.75, "low": 1268.0, "close": 1268.5, "volume": 1239}, {"time": 1199415480, "open": 1268.25, "high": 1268.5, "low": 1267.75, "close": 1267.75, "volume": 1272}, {"time": 1199415540, "open": 1268.0, "high": 1268.25, "low": 1267.5, "close": 1268.0, "volume": 1166}, {"time": 1199415600, "open": 1268.0, "high": 1268.0, "low": 1267.25, "close": 1267.5, "volume": 1041}, {"time": 1199415660, "open": 1267.5, "high": 1267.75, "low": 1267.0, "close": 1267.25, "volume": 869}, {"time": 1199415720, "open": 1267.5, "high": 1267.5, "low": 1267.0, "close": 1267.0, "volume": 387}, {"time": 1199415780, "open": 1267.25, "high": 1267.75, "low": 1267.0, "close": 1267.25, "volume": 2098}, {"time": 1199415840, "open": 1267.25, "high": 1267.5, "low": 1266.75, "close": 1267.5, "volume": 1173}, {"time": 1199415900, "open": 1267.5, "high": 1267.5, "low": 1266.0, "close": 1266.25, "volume": 1868}, {"time": 1199415960, "open": 1266.25, "high": 1267.5, "low": 1266.0, "close": 1267.25, "volume": 4566}, {"time": 1199416020, "open": 1267.25, "high": 1267.5, "low": 1267.25, "close": 1267.5, "volume": 471}, {"time": 1199416080, "open": 1267.5, "high": 1267.75, "low": 1267.0, "close": 1267.0, "volume": 986}, {"time": 1199416140, "open": 1267.0, "high": 1267.25, "low": 1266.5, "close": 1266.75, "volume": 1083}, {"time": 1199416200, "open": 1267.0, "high": 1267.0, "low": 1266.5, "close": 1266.75, "volume": 531}, {"time": 1199416260, "open": 1266.75, "high": 1267.0, "low": 1266.0, "close": 1266.25, "volume": 1812}, {"time": 1199416320, "open": 1266.25, "high": 1267.5, "low": 1266.25, "close": 1267.0, "volume": 2161}, {"time": 1199416380, "open": 1267.25, "high": 1268.25, "low": 1266.75, "close": 1268.0, "volume": 3175}, {"time": 1199416440, "open": 1267.75, "high": 1268.5, "low": 1267.25, "close": 1268.0, "volume": 3057}, {"time": 1199416500, "open": 1268.0, "high": 1268.0, "low": 1267.25, "close": 1267.5, "volume": 1741}, {"time": 1199416560, "open": 1267.5, "high": 1268.25, "low": 1267.5, "close": 1267.75, "volume": 543}, {"time": 1199416620, "open": 1268.0, "high": 1268.75, "low": 1268.0, "close": 1268.75, "volume": 2067}, {"time": 1199416680, "open": 1268.75, "high": 1268.75, "low": 1267.75, "close": 1268.0, "volume": 1585}, {"time": 1199416740, "open": 1268.0, "high": 1268.0, "low": 1266.75, "close": 1267.0, "volume": 1605}, {"time": 1199416800, "open": 1267.0, "high": 1267.5, "low": 1266.75, "close": 1267.0, "volume": 1039}, {"time": 1199416860, "open": 1266.75, "high": 1267.25, "low": 1266.5, "close": 1267.0, "volume": 1615}, {"time": 1199416920, "open": 1267.25, "high": 1267.25, "low": 1266.0, "close": 1266.0, "volume": 2859}, {"time": 1199416980, "open": 1266.0, "high": 1266.25, "low": 1264.75, "close": 1265.5, "volume": 8481}, {"time": 1199417040, "open": 1265.5, "high": 1266.25, "low": 1265.25, "close": 1265.75, "volume": 2732}, {"time": 1199417100, "open": 1265.75, "high": 1265.75, "low": 1264.75, "close": 1265.0, "volume": 1889}, {"time": 1199417160, "open": 1265.0, "high": 1265.25, "low": 1264.25, "close": 1264.75, "volume": 4622}, {"time": 1199417220, "open": 1264.75, "high": 1266.25, "low": 1264.75, "close": 1266.0, "volume": 3045}, {"time": 1199417280, "open": 1265.75, "high": 1266.5, "low": 1265.5, "close": 1266.0, "volume": 3023}, {"time": 1199417340, "open": 1266.0, "high": 1266.75, "low": 1266.0, "close": 1266.5, "volume": 1658}, {"time": 1199417400, "open": 1266.25, "high": 1266.5, "low": 1265.75, "close": 1266.25, "volume": 1991}, {"time": 1199417460, "open": 1266.25, "high": 1266.75, "low": 1266.25, "close": 1266.25, "volume": 833}, {"time": 1199417520, "open": 1266.25, "high": 1266.5, "low": 1266.0, "close": 1266.5, "volume": 522}, {"time": 1199417580, "open": 1266.5, "high": 1267.0, "low": 1266.25, "close": 1266.75, "volume": 867}, {"time": 1199417640, "open": 1266.75, "high": 1266.75, "low": 1266.0, "close": 1266.25, "volume": 757}, {"time": 1199417700, "open": 1266.25, "high": 1266.5, "low": 1265.5, "close": 1265.5, "volume": 1968}, {"time": 1199417760, "open": 1265.25, "high": 1265.5, "low": 1263.75, "close": 1263.75, "volume": 6856}, {"time": 1199417820, "open": 1264.0, "high": 1264.0, "low": 1262.75, "close": 1263.0, "volume": 8680}, {"time": 1199417880, "open": 1263.0, "high": 1263.25, "low": 1261.5, "close": 1262.5, "volume": 12119}, {"time": 1199417940, "open": 1262.5, "high": 1263.5, "low": 1262.25, "close": 1263.25, "volume": 3870}, {"time": 1199418000, "open": 1263.0, "high": 1263.25, "low": 1262.0, "close": 1262.5, "volume": 6101}, {"time": 1199418060, "open": 1262.75, "high": 1263.5, "low": 1262.0, "close": 1262.5, "volume": 4650}, {"time": 1199418120, "open": 1262.5, "high": 1263.0, "low": 1262.5, "close": 1263.0, "volume": 1613}, {"time": 1199418180, "open": 1263.0, "high": 1264.0, "low": 1263.0, "close": 1263.5, "volume": 6083}, {"time": 1199418240, "open": 1263.75, "high": 1264.5, "low": 1263.0, "close": 1263.25, "volume": 4145}, {"time": 1199418300, "open": 1263.25, "high": 1263.5, "low": 1262.75, "close": 1263.5, "volume": 3897}, {"time": 1199418360, "open": 1263.5, "high": 1263.5, "low": 1262.25, "close": 1262.75, "volume": 3488}, {"time": 1199418420, "open": 1262.75, "high": 1263.75, "low": 1262.5, "close": 1263.5, "volume": 2291}, {"time": 1199418480, "open": 1263.5, "high": 1264.0, "low": 1263.25, "close": 1263.75, "volume": 1826}, {"time": 1199418540, "open": 1264.0, "high": 1265.0, "low": 1263.5, "close": 1265.0, "volume": 5614}, {"time": 1199418600, "open": 1265.0, "high": 1266.25, "low": 1264.75, "close": 1266.0, "volume": 5370}, {"time": 1199418660, "open": 1266.0, "high": 1266.75, "low": 1266.0, "close": 1266.0, "volume": 4622}, {"time": 1199418720, "open": 1266.0, "high": 1266.5, "low": 1265.5, "close": 1266.25, "volume": 2720}, {"time": 1199418780, "open": 1266.25, "high": 1267.0, "low": 1265.75, "close": 1267.0, "volume": 4334}, {"time": 1199418840, "open": 1267.0, "high": 1268.5, "low": 1266.75, "close": 1267.75, "volume": 8133}, {"time": 1199418900, "open": 1268.0, "high": 1268.25, "low": 1267.5, "close": 1268.25, "volume": 2447}, {"time": 1199418960, "open": 1268.0, "high": 1268.25, "low": 1267.75, "close": 1267.75, "volume": 1458}, {"time": 1199419020, "open": 1267.75, "high": 1268.0, "low": 1266.5, "close": 1266.75, "volume": 4421}, {"time": 1199419080, "open": 1267.0, "high": 1268.5, "low": 1266.75, "close": 1267.0, "volume": 3294}, {"time": 1199419140, "open": 1267.0, "high": 1267.5, "low": 1266.5, "close": 1266.75, "volume": 2612}, {"time": 1199419200, "open": 1266.5, "high": 1266.75, "low": 1264.75, "close": 1265.0, "volume": 7208}, {"time": 1199419260, "open": 1265.25, "high": 1266.0, "low": 1265.0, "close": 1265.5, "volume": 3101}, {"time": 1199419320, "open": 1265.5, "high": 1265.75, "low": 1263.75, "close": 1265.0, "volume": 5304}, {"time": 1199419380, "open": 1265.0, "high": 1265.25, "low": 1264.0, "close": 1264.5, "volume": 3358}, {"time": 1199419440, "open": 1264.75, "high": 1265.0, "low": 1263.5, "close": 1264.75, "volume": 3503}, {"time": 1199419500, "open": 1264.5, "high": 1265.0, "low": 1264.25, "close": 1264.5, "volume": 1502}, {"time": 1199419560, "open": 1264.5, "high": 1264.5, "low": 1262.5, "close": 1263.5, "volume": 7239}, {"time": 1199419620, "open": 1263.5, "high": 1263.75, "low": 1263.0, "close": 1263.0, "volume": 1544}, {"time": 1199419680, "open": 1263.0, "high": 1265.0, "low": 1262.75, "close": 1264.75, "volume": 6130}, {"time": 1199419740, "open": 1264.75, "high": 1265.0, "low": 1263.5, "close": 1264.0, "volume": 4331}, {"time": 1199419800, "open": 1264.25, "high": 1264.75, "low": 1262.75, "close": 1264.5, "volume": 3134}, {"time": 1199419860, "open": 1264.75, "high": 1264.75, "low": 1263.0, "close": 1263.25, "volume": 3507}, {"time": 1199419920, "open": 1263.25, "high": 1264.25, "low": 1263.0, "close": 1263.0, "volume": 2419}, {"time": 1199419980, "open": 1263.0, "high": 1263.25, "low": 1261.75, "close": 1262.75, "volume": 6769}, {"time": 1199420040, "open": 1262.75, "high": 1263.25, "low": 1262.0, "close": 1263.25, "volume": 2529}, {"time": 1199420100, "open": 1263.0, "high": 1263.25, "low": 1261.75, "close": 1262.0, "volume": 3610}, {"time": 1199420160, "open": 1261.75, "high": 1263.0, "low": 1261.5, "close": 1263.0, "volume": 5629}, {"time": 1199420220, "open": 1262.75, "high": 1263.25, "low": 1262.5, "close": 1263.25, "volume": 1547}, {"time": 1199420280, "open": 1263.25, "high": 1264.75, "low": 1263.0, "close": 1263.75, "volume": 6350}, {"time": 1199420340, "open": 1263.75, "high": 1264.5, "low": 1262.75, "close": 1264.25, "volume": 3742}, {"time": 1199420400, "open": 1264.0, "high": 1264.25, "low": 1261.5, "close": 1262.25, "volume": 8460}, {"time": 1199420460, "open": 1262.25, "high": 1262.75, "low": 1260.5, "close": 1260.75, "volume": 9844}, {"time": 1199420520, "open": 1260.5, "high": 1261.0, "low": 1260.0, "close": 1260.75, "volume": 5143}, {"time": 1199420580, "open": 1260.5, "high": 1261.0, "low": 1259.5, "close": 1260.0, "volume": 6601}, {"time": 1199420640, "open": 1260.0, "high": 1261.0, "low": 1259.75, "close": 1260.75, "volume": 4120}, {"time": 1199420700, "open": 1260.75, "high": 1261.0, "low": 1260.25, "close": 1261.0, "volume": 1994}, {"time": 1199420760, "open": 1260.75, "high": 1261.75, "low": 1260.75, "close": 1261.75, "volume": 3928}, {"time": 1199420820, "open": 1261.5, "high": 1261.75, "low": 1260.5, "close": 1260.75, "volume": 2630}, {"time": 1199420880, "open": 1260.75, "high": 1261.25, "low": 1259.75, "close": 1260.0, "volume": 2137}, {"time": 1199420940, "open": 1260.0, "high": 1260.5, "low": 1259.5, "close": 1259.75, "volume": 3963}, {"time": 1199421000, "open": 1259.75, "high": 1260.5, "low": 1259.5, "close": 1260.5, "volume": 3366}, {"time": 1199421060, "open": 1260.5, "high": 1260.5, "low": 1259.5, "close": 1260.5, "volume": 4418}, {"time": 1199421120, "open": 1260.25, "high": 1261.25, "low": 1260.0, "close": 1260.75, "volume": 2561}, {"time": 1199421180, "open": 1260.75, "high": 1260.75, "low": 1259.0, "close": 1259.25, "volume": 7158}, {"time": 1199421240, "open": 1259.25, "high": 1260.75, "low": 1259.0, "close": 1260.5, "volume": 6791}, {"time": 1199421300, "open": 1260.5, "high": 1261.0, "low": 1260.25, "close": 1261.0, "volume": 1502}, {"time": 1199421360, "open": 1261.0, "high": 1261.0, "low": 1260.0, "close": 1260.25, "volume": 2357}, {"time": 1199421420, "open": 1260.0, "high": 1260.25, "low": 1259.0, "close": 1259.25, "volume": 5161}, {"time": 1199421480, "open": 1259.5, "high": 1259.5, "low": 1258.75, "close": 1259.0, "volume": 6978}, {"time": 1199421540, "open": 1259.0, "high": 1259.5, "low": 1258.5, "close": 1259.0, "volume": 4839}, {"time": 1199421600, "open": 1259.0, "high": 1259.0, "low": 1258.0, "close": 1258.25, "volume": 6027}, {"time": 1199421660, "open": 1258.5, "high": 1258.75, "low": 1258.0, "close": 1258.5, "volume": 4624}, {"time": 1199421720, "open": 1258.25, "high": 1258.75, "low": 1258.0, "close": 1258.25, "volume": 3540}, {"time": 1199421780, "open": 1258.0, "high": 1258.25, "low": 1257.5, "close": 1258.0, "volume": 4790}, {"time": 1199421840, "open": 1258.0, "high": 1258.25, "low": 1257.5, "close": 1258.25, "volume": 4870}, {"time": 1199421900, "open": 1258.25, "high": 1259.5, "low": 1258.0, "close": 1259.25, "volume": 6760}, {"time": 1199421960, "open": 1259.0, "high": 1259.75, "low": 1259.0, "close": 1259.75, "volume": 3514}, {"time": 1199422020, "open": 1259.75, "high": 1260.25, "low": 1259.25, "close": 1259.75, "volume": 5035}, {"time": 1199422080, "open": 1259.5, "high": 1260.25, "low": 1259.5, "close": 1259.75, "volume": 3546}, {"time": 1199422140, "open": 1259.75, "high": 1260.0, "low": 1259.0, "close": 1259.25, "volume": 2446}, {"time": 1199422200, "open": 1259.25, "high": 1259.75, "low": 1259.0, "close": 1259.25, "volume": 1365}, {"time": 1199422260, "open": 1259.5, "high": 1260.0, "low": 1259.25, "close": 1259.75, "volume": 1764}, {"time": 1199422320, "open": 1259.75, "high": 1260.0, "low": 1258.0, "close": 1258.25, "volume": 2845}, {"time": 1199422380, "open": 1258.0, "high": 1258.5, "low": 1257.5, "close": 1258.0, "volume": 5809}, {"time": 1199422440, "open": 1258.0, "high": 1258.25, "low": 1257.0, "close": 1257.0, "volume": 11556}, {"time": 1199422500, "open": 1257.0, "high": 1258.5, "low": 1256.0, "close": 1258.5, "volume": 16076}, {"time": 1199422560, "open": 1258.5, "high": 1259.5, "low": 1258.25, "close": 1259.0, "volume": 5321}, {"time": 1199422620, "open": 1259.0, "high": 1260.25, "low": 1258.75, "close": 1260.0, "volume": 5071}, {"time": 1199422680, "open": 1260.0, "high": 1261.5, "low": 1259.25, "close": 1261.5, "volume": 6475}, {"time": 1199422740, "open": 1261.5, "high": 1262.25, "low": 1261.0, "close": 1261.25, "volume": 9406}, {"time": 1199422800, "open": 1261.25, "high": 1262.0, "low": 1261.0, "close": 1261.75, "volume": 6307}, {"time": 1199422860, "open": 1261.75, "high": 1262.5, "low": 1261.25, "close": 1261.25, "volume": 5515}, {"time": 1199422920, "open": 1261.25, "high": 1261.25, "low": 1260.25, "close": 1260.75, "volume": 3078}, {"time": 1199422980, "open": 1260.75, "high": 1262.5, "low": 1260.5, "close": 1262.5, "volume": 7660}, {"time": 1199423040, "open": 1262.5, "high": 1263.0, "low": 1261.5, "close": 1261.75, "volume": 7520}, {"time": 1199423100, "open": 1261.75, "high": 1262.5, "low": 1261.25, "close": 1261.25, "volume": 5059}, {"time": 1199423160, "open": 1261.25, "high": 1262.5, "low": 1261.0, "close": 1262.25, "volume": 2762}, {"time": 1199423220, "open": 1262.5, "high": 1263.75, "low": 1262.25, "close": 1263.75, "volume": 7524}, {"time": 1199423280, "open": 1263.5, "high": 1264.0, "low": 1262.75, "close": 1262.75, "volume": 5476}, {"time": 1199423340, "open": 1263.0, "high": 1263.0, "low": 1261.0, "close": 1262.5, "volume": 7289}, {"time": 1199423400, "open": 1262.25, "high": 1262.75, "low": 1261.25, "close": 1262.75, "volume": 4364}, {"time": 1199423460, "open": 1262.5, "high": 1262.75, "low": 1261.5, "close": 1262.25, "volume": 4753}, {"time": 1199423520, "open": 1262.25, "high": 1262.5, "low": 1261.5, "close": 1261.5, "volume": 2616}, {"time": 1199423580, "open": 1261.5, "high": 1261.75, "low": 1261.0, "close": 1261.0, "volume": 2651}, {"time": 1199423640, "open": 1261.0, "high": 1261.0, "low": 1259.75, "close": 1260.25, "volume": 5069}, {"time": 1199423700, "open": 1260.0, "high": 1260.75, "low": 1258.75, "close": 1259.5, "volume": 6715}, {"time": 1199423760, "open": 1259.25, "high": 1260.25, "low": 1258.75, "close": 1259.5, "volume": 2929}, {"time": 1199423820, "open": 1259.5, "high": 1260.5, "low": 1259.25, "close": 1260.5, "volume": 4041}, {"time": 1199423880, "open": 1260.5, "high": 1262.0, "low": 1260.5, "close": 1262.0, "volume": 4263}, {"time": 1199423940, "open": 1262.0, "high": 1262.5, "low": 1260.75, "close": 1261.0, "volume": 3859}, {"time": 1199424000, "open": 1261.0, "high": 1261.25, "low": 1259.75, "close": 1259.75, "volume": 2932}, {"time": 1199424060, "open": 1259.75, "high": 1260.5, "low": 1259.0, "close": 1260.5, "volume": 3353}, {"time": 1199424120, "open": 1260.5, "high": 1260.75, "low": 1259.5, "close": 1259.75, "volume": 3550}, {"time": 1199424180, "open": 1259.75, "high": 1259.75, "low": 1257.75, "close": 1257.75, "volume": 7246}, {"time": 1199424240, "open": 1257.75, "high": 1258.75, "low": 1257.75, "close": 1258.75, "volume": 6215}, {"time": 1199424300, "open": 1258.75, "high": 1259.5, "low": 1258.75, "close": 1259.0, "volume": 2130}, {"time": 1199424360, "open": 1258.75, "high": 1260.0, "low": 1258.75, "close": 1259.5, "volume": 3688}, {"time": 1199424420, "open": 1259.5, "high": 1260.25, "low": 1259.25, "close": 1259.75, "volume": 2493}, {"time": 1199424480, "open": 1260.0, "high": 1261.75, "low": 1259.75, "close": 1261.5, "volume": 3593}, {"time": 1199424540, "open": 1261.5, "high": 1264.25, "low": 1261.25, "close": 1262.25, "volume": 11030}, {"time": 1199424600, "open": 1262.5, "high": 1264.25, "low": 1262.25, "close": 1263.0, "volume": 8187}, {"time": 1199424660, "open": 1263.0, "high": 1263.5, "low": 1262.25, "close": 1262.75, "volume": 4862}, {"time": 1199424720, "open": 1262.75, "high": 1263.0, "low": 1262.0, "close": 1262.25, "volume": 3127}, {"time": 1199424780, "open": 1262.25, "high": 1262.5, "low": 1261.25, "close": 1261.75, "volume": 3625}, {"time": 1199424840, "open": 1261.75, "high": 1262.0, "low": 1261.5, "close": 1261.5, "volume": 1316}, {"time": 1199424900, "open": 1261.5, "high": 1261.75, "low": 1260.5, "close": 1261.5, "volume": 5470}, {"time": 1199424960, "open": 1261.75, "high": 1262.25, "low": 1261.25, "close": 1262.0, "volume": 2477}, {"time": 1199425020, "open": 1262.0, "high": 1262.0, "low": 1260.0, "close": 1260.0, "volume": 4415}, {"time": 1199425080, "open": 1260.0, "high": 1261.25, "low": 1259.75, "close": 1261.0, "volume": 5325}, {"time": 1199425140, "open": 1261.0, "high": 1261.75, "low": 1260.25, "close": 1261.75, "volume": 2999}, {"time": 1199425200, "open": 1261.75, "high": 1262.0, "low": 1259.5, "close": 1259.5, "volume": 8451}, {"time": 1199425260, "open": 1259.5, "high": 1260.75, "low": 1259.5, "close": 1260.25, "volume": 4115}, {"time": 1199425320, "open": 1260.25, "high": 1261.0, "low": 1260.25, "close": 1260.25, "volume": 6694}, {"time": 1199425380, "open": 1260.25, "high": 1261.25, "low": 1260.25, "close": 1260.75, "volume": 4684}, {"time": 1199425440, "open": 1260.75, "high": 1260.75, "low": 1258.5, "close": 1259.5, "volume": 9091}, {"time": 1199425500, "open": 1259.5, "high": 1259.75, "low": 1258.75, "close": 1259.5, "volume": 5416}, {"time": 1199425560, "open": 1259.5, "high": 1260.0, "low": 1258.25, "close": 1258.5, "volume": 4172}, {"time": 1199425620, "open": 1258.5, "high": 1258.5, "low": 1256.75, "close": 1257.25, "volume": 10968}, {"time": 1199425680, "open": 1257.25, "high": 1258.5, "low": 1256.5, "close": 1257.75, "volume": 7346}, {"time": 1199425740, "open": 1257.75, "high": 1257.75, "low": 1256.75, "close": 1257.25, "volume": 5372}, {"time": 1199425800, "open": 1257.25, "high": 1257.5, "low": 1255.5, "close": 1256.25, "volume": 12774}, {"time": 1199425860, "open": 1256.25, "high": 1257.25, "low": 1255.5, "close": 1257.25, "volume": 8465}, {"time": 1199425920, "open": 1257.25, "high": 1258.5, "low": 1257.0, "close": 1258.5, "volume": 6879}, {"time": 1199425980, "open": 1258.25, "high": 1258.25, "low": 1256.5, "close": 1257.25, "volume": 8584}, {"time": 1199426040, "open": 1257.5, "high": 1257.5, "low": 1256.5, "close": 1256.75, "volume": 4639}, {"time": 1199426100, "open": 1256.5, "high": 1257.25, "low": 1256.0, "close": 1256.25, "volume": 6529}, {"time": 1199426160, "open": 1256.25, "high": 1256.25, "low": 1255.5, "close": 1256.25, "volume": 11243}, {"time": 1199426220, "open": 1256.0, "high": 1256.5, "low": 1255.75, "close": 1256.25, "volume": 8009}, {"time": 1199426280, "open": 1256.5, "high": 1256.75, "low": 1256.0, "close": 1256.25, "volume": 11243}, {"time": 1199426340, "open": 1256.0, "high": 1256.25, "low": 1255.25, "close": 1255.5, "volume": 28177}, {"time": 1199426400, "open": 1255.25, "high": 1257.5, "low": 1255.0, "close": 1257.25, "volume": 30464}, {"time": 1199426460, "open": 1257.25, "high": 1257.5, "low": 1256.75, "close": 1257.25, "volume": 11739}, {"time": 1199426520, "open": 1257.25, "high": 1257.25, "low": 1256.0, "close": 1256.5, "volume": 6660}, {"time": 1199426580, "open": 1256.5, "high": 1257.0, "low": 1256.25, "close": 1256.75, "volume": 5014}, {"time": 1199426640, "open": 1256.75, "high": 1256.75, "low": 1256.0, "close": 1256.5, "volume": 4942}, {"time": 1199426700, "open": 1256.5, "high": 1256.75, "low": 1256.25, "close": 1256.75, "volume": 5743}, {"time": 1199426760, "open": 1256.75, "high": 1257.75, "low": 1256.5, "close": 1257.75, "volume": 7770}, {"time": 1199426820, "open": 1257.75, "high": 1258.0, "low": 1257.5, "close": 1257.75, "volume": 2500}, {"time": 1199426880, "open": 1258.0, "high": 1258.25, "low": 1257.75, "close": 1257.75, "volume": 5344}, {"time": 1199426940, "open": 1258.0, "high": 1258.5, "low": 1257.75, "close": 1258.5, "volume": 4155}, {"time": 1199427000, "open": 1258.25, "high": 1259.5, "low": 1258.25, "close": 1258.75, "volume": 8399}, {"time": 1199427060, "open": 1259.0, "high": 1259.25, "low": 1258.75, "close": 1259.25, "volume": 2881}, {"time": 1199427120, "open": 1259.25, "high": 1260.25, "low": 1259.0, "close": 1260.0, "volume": 6511}, {"time": 1199427180, "open": 1260.0, "high": 1260.25, "low": 1259.75, "close": 1260.25, "volume": 3149}, {"time": 1199427240, "open": 1260.0, "high": 1260.75, "low": 1259.5, "close": 1260.0, "volume": 10104}]