[{"time": 1371369600, "open": 1544.5, "high": 1545.25, "low": 1544.25, "close": 1544.25, "volume": 1303}, {"time": 1371369660, "open": 1544.25, "high": 1544.5, "low": 1543.75, "close": 1543.75, "volume": 438}, {"time": 1371369720, "open": 1544.0, "high": 1545.0, "low": 1544.0, "close": 1545.0, "volume": 460}, {"time": 1371369780, "open": 1545.0, "high": 1545.25, "low": 1545.0, "close": 1545.0, "volume": 211}, {"time": 1371369840, "open": 1545.0, "high": 1545.25, "low": 1545.0, "close": 1545.25, "volume": 65}, {"time": 1371369900, "open": 1545.25, "high": 1546.25, "low": 1545.0, "close": 1546.25, "volume": 1082}, {"time": 1371369960, "open": 1546.0, "high": 1546.25, "low": 1545.75, "close": 1546.0, "volume": 208}, {"time": 1371370020, "open": 1546.0, "high": 1546.0, "low": 1545.75, "close": 1545.75, "volume": 11}, {"time": 1371370080, "open": 1545.75, "high": 1546.25, "low": 1545.75, "close": 1546.25, "volume": 202}, {"time": 1371370140, "open": 1546.25, "high": 1546.5, "low": 1546.0, "close": 1546.25, "volume": 248}, {"time": 1371370200, "open": 1546.25, "high": 1546.25, "low": 1546.25, "close": 1546.25, "volume": 12}, {"time": 1371370320, "open": 1546.0, "high": 1546.5, "low": 1546.0, "close": 1546.5, "volume": 329}, {"time": 1371370380, "open": 1546.75, "high": 1546.75, "low": 1546.25, "close": 1546.25, "volume": 189}, {"time": 1371370440, "open": 1546.25, "high": 1546.25, "low": 1546.0, "close": 1546.0, "volume": 4}, {"time": 1371370500, "open": 1546.25, "high": 1546.25, "low": 1546.0, "close": 1546.0, "volume": 4}, {"time": 1371370560, "open": 1546.0, "high": 1546.25, "low": 1546.0, "close": 1546.25, "volume": 52}, {"time": 1371370620, "open": 1546.25, "high": 1546.25, "low": 1546.0, "close": 1546.0, "volume": 18}, {"time": 1371370680, "open": 1546.25, "high": 1546.25, "low": 1546.25, "close": 1546.25, "volume": 16}, {"time": 1371370800, "open": 1546.25, "high": 1546.25, "low": 1546.0, "close": 1546.25, "volume": 14}, {"time": 1371370860, "open": 1546.25, "high": 1546.25, "low": 1546.0, "close": 1546.25, "volume": 283}, {"time": 1371370920, "open": 1546.25, "high": 1546.5, "low": 1546.25, "close": 1546.5, "volume": 53}, {"time": 1371370980, "open": 1546.5, "high": 1546.5, "low": 1546.25, "close": 1546.25, "volume": 47}, {"time": 1371371040, "open": 1546.25, "high": 1546.25, "low": 1546.25, "close": 1546.25, "volume": 6}, {"time": 1371371100, "open": 1546.25, "high": 1546.25, "low": 1546.25, "close": 1546.25, "volume": 68}, {"time": 1371371160, "open": 1546.25, "high": 1546.25, "low": 1546.25, "close": 1546.25, "volume": 38}, {"time": 1371371220, "open": 1546.25, "high": 1546.5, "low": 1546.25, "close": 1546.25, "volume": 226}, {"time": 1371371280, "open": 1546.25, "high": 1546.25, "low": 1546.25, "close": 1546.25, "volume": 20}, {"time": 1371371340, "open": 1546.25, "high": 1546.25, "low": 1546.25, "close": 1546.25, "volume": 12}, {"time": 1371371400, "open": 1546.5, "high": 1546.5, "low": 1546.5, "close": 1546.5, "volume": 25}, {"time": 1371371460, "open": 1546.5, "high": 1546.5, "low": 1546.5, "close": 1546.5, "volume": 1}, {"time": 1371371520, "open": 1546.25, "high": 1546.5, "low": 1546.25, "close": 1546.5, "volume": 40}, {"time": 1371371580, "open": 1546.5, "high": 1546.75, "low": 1546.5, "close": 1546.75, "volume": 59}, {"time": 1371371640, "open": 1546.75, "high": 1546.75, "low": 1546.5, "close": 1546.75, "volume": 28}, {"time": 1371371760, "open": 1546.75, "high": 1546.75, "low": 1546.75, "close": 1546.75, "volume": 4}, {"time": 1371371820, "open": 1546.75, "high": 1547.0, "low": 1546.5, "close": 1547.0, "volume": 379}, {"time": 1371371880, "open": 1547.0, "high": 1547.25, "low": 1546.75, "close": 1547.0, "volume": 50}, {"time": 1371371940, "open": 1546.75, "high": 1546.75, "low": 1546.5, "close": 1546.5, "volume": 85}, {"time": 1371372000, "open": 1546.5, "high": 1546.5, "low": 1546.0, "close": 1546.0, "volume": 73}, {"time": 1371372060, "open": 1546.25, "high": 1546.5, "low": 1546.25, "close": 1546.25, "volume": 63}, {"time": 1371372120, "open": 1546.5, "high": 1546.5, "low": 1546.25, "close": 1546.25, "volume": 5}, {"time": 1371372180, "open": 1546.25, "high": 1546.5, "low": 1546.25, "close": 1546.25, "volume": 13}, {"time": 1371372240, "open": 1546.25, "high": 1546.5, "low": 1546.25, "close": 1546.5, "volume": 3}, {"time": 1371372300, "open": 1546.25, "high": 1546.25, "low": 1546.25, "close": 1546.25, "volume": 5}, {"time": 1371372360, "open": 1546.25, "high": 1546.5, "low": 1546.0, "close": 1546.0, "volume": 46}, {"time": 1371372420, "open": 1546.25, "high": 1546.5, "low": 1546.25, "close": 1546.25, "volume": 21}, {"time": 1371372480, "open": 1546.25, "high": 1546.25, "low": 1546.0, "close": 1546.0, "volume": 6}, {"time": 1371372540, "open": 1546.0, "high": 1546.25, "low": 1546.0, "close": 1546.0, "volume": 4}, {"time": 1371372600, "open": 1546.0, "high": 1546.25, "low": 1546.0, "close": 1546.0, "volume": 6}, {"time": 1371372660, "open": 1546.25, "high": 1546.25, "low": 1546.0, "close": 1546.0, "volume": 18}, {"time": 1371372720, "open": 1546.0, "high": 1546.25, "low": 1546.0, "close": 1546.25, "volume": 95}, {"time": 1371372780, "open": 1546.25, "high": 1546.5, "low": 1546.25, "close": 1546.5, "volume": 4}, {"time": 1371372840, "open": 1546.25, "high": 1546.25, "low": 1546.0, "close": 1546.0, "volume": 30}, {"time": 1371372960, "open": 1546.25, "high": 1546.25, "low": 1546.25, "close": 1546.25, "volume": 10}, {"time": 1371373140, "open": 1546.0, "high": 1546.0, "low": 1545.75, "close": 1546.0, "volume": 141}, {"time": 1371373200, "open": 1546.0, "high": 1546.0, "low": 1546.0, "close": 1546.0, "volume": 28}, {"time": 1371373260, "open": 1546.0, "high": 1546.0, "low": 1546.0, "close": 1546.0, "volume": 1}, {"time": 1371373320, "open": 1546.25, "high": 1546.5, "low": 1546.25, "close": 1546.5, "volume": 46}, {"time": 1371373380, "open": 1546.5, "high": 1546.5, "low": 1546.5, "close": 1546.5, "volume": 2}, {"time": 1371373440, "open": 1546.5, "high": 1546.5, "low": 1546.25, "close": 1546.25, "volume": 8}, {"time": 1371373500, "open": 1546.25, "high": 1546.5, "low": 1546.25, "close": 1546.5, "volume": 3}, {"time": 1371373560, "open": 1546.5, "high": 1546.5, "low": 1546.25, "close": 1546.25, "volume": 7}, {"time": 1371373620, "open": 1546.25, "high": 1546.75, "low": 1546.25, "close": 1546.75, "volume": 45}, {"time": 1371373680, "open": 1546.75, "high": 1546.75, "low": 1546.5, "close": 1546.75, "volume": 65}, {"time": 1371373740, "open": 1546.75, "high": 1546.75, "low": 1546.75, "close": 1546.75, "volume": 1}, {"time": 1371373800, "open": 1546.75, "high": 1546.75, "low": 1546.75, "close": 1546.75, "volume": 43}, {"time": 1371373860, "open": 1546.75, "high": 1546.75, "low": 1546.5, "close": 1546.5, "volume": 12}, {"time": 1371373920, "open": 1546.5, "high": 1546.5, "low": 1546.25, "close": 1546.25, "volume": 142}, {"time": 1371373980, "open": 1546.5, "high": 1546.5, "low": 1546.5, "close": 1546.5, "volume": 3}, {"time": 1371374040, "open": 1546.5, "high": 1546.5, "low": 1546.5, "close": 1546.5, "volume": 6}, {"time": 1371374220, "open": 1546.25, "high": 1546.5, "low": 1546.25, "close": 1546.5, "volume": 13}, {"time": 1371374280, "open": 1546.5, "high": 1546.5, "low": 1546.25, "close": 1546.25, "volume": 15}, {"time": 1371374340, "open": 1546.25, "high": 1546.25, "low": 1546.25, "close": 1546.25, "volume": 1}, {"time": 1371374400, "open": 1546.25, "high": 1546.25, "low": 1546.0, "close": 1546.0, "volume": 14}, {"time": 1371374460, "open": 1546.25, "high": 1546.25, "low": 1546.25, "close": 1546.25, "volume": 1}, {"time": 1371374580, "open": 1546.0, "high": 1546.25, "low": 1546.0, "close": 1546.25, "volume": 5}, {"time": 1371374640, "open": 1546.25, "high": 1546.25, "low": 1546.25, "close": 1546.25, "volume": 2}, {"time": 1371374700, "open": 1546.25, "high": 1546.25, "low": 1546.25, "close": 1546.25, "volume": 9}, {"time": 1371374760, "open": 1546.25, "high": 1546.25, "low": 1546.25, "close": 1546.25, "volume": 7}, {"time": 1371374820, "open": 1546.25, "high": 1546.25, "low": 1546.25, "close": 1546.25, "volume": 74}, {"time": 1371374880, "open": 1546.25, "high": 1546.25, "low": 1546.0, "close": 1546.25, "volume": 67}, {"time": 1371375000, "open": 1546.25, "high": 1546.25, "low": 1546.25, "close": 1546.25, "volume": 5}, {"time": 1371375060, "open": 1546.25, "high": 1546.25, "low": 1546.0, "close": 1546.0, "volume": 28}, {"time": 1371375120, "open": 1546.25, "high": 1546.25, "low": 1546.25, "close": 1546.25, "volume": 2}, {"time": 1371375180, "open": 1546.25, "high": 1546.25, "low": 1546.0, "close": 1546.0, "volume": 27}, {"time": 1371375300, "open": 1546.0, "high": 1546.0, "low": 1546.0, "close": 1546.0, "volume": 5}, {"time": 1371375360, "open": 1546.25, "high": 1546.25, "low": 1546.25, "close": 1546.25, "volume": 1}, {"time": 1371375420, "open": 1546.25, "high": 1546.25, "low": 1546.25, "close": 1546.25, "volume": 5}, {"time": 1371375480, "open": 1546.25, "high": 1546.25, "low": 1546.0, "close": 1546.0, "volume": 117}, {"time": 1371375540, "open": 1546.25, "high": 1546.25, "low": 1546.25, "close": 1546.25, "volume": 6}, {"time": 1371375600, "open": 1546.25, "high": 1546.25, "low": 1546.25, "close": 1546.25, "volume": 2}, {"time": 1371375660, "open": 1546.25, "high": 1546.25, "low": 1546.25, "close": 1546.25, "volume": 2}, {"time": 1371375720, "open": 1546.25, "high": 1546.25, "low": 1546.25, "close": 1546.25, "volume": 3}, {"time": 1371375840, "open": 1546.25, "high": 1546.5, "low": 1546.25, "close": 1546.25, "volume": 222}, {"time": 1371375900, "open": 1546.25, "high": 1546.5, "low": 1546.25, "close": 1546.5, "volume": 3}, {"time": 1371375960, "open": 1546.25, "high": 1546.75, "low": 1546.25, "close": 1546.75, "volume": 182}, {"time": 1371376020, "open": 1546.5, "high": 1546.75, "low": 1546.5, "close": 1546.75, "volume": 3}, {"time": 1371376080, "open": 1546.75, "high": 1546.75, "low": 1546.5, "close": 1546.75, "volume": 43}, {"time": 1371376140, "open": 1546.75, "high": 1546.75, "low": 1546.75, "close": 1546.75, "volume": 6}, {"time": 1371376200, "open": 1546.75, "high": 1546.75, "low": 1546.5, "close": 1546.75, "volume": 16}, {"time": 1371376260, "open": 1546.75, "high": 1546.75, "low": 1546.75, "close": 1546.75, "volume": 3}, {"time": 1371376320, "open": 1546.75, "high": 1547.25, "low": 1546.75, "close": 1547.25, "volume": 292}, {"time": 1371376380, "open": 1547.25, "high": 1547.25, "low": 1547.0, "close": 1547.0, "volume": 212}, {"time": 1371376440, "open": 1547.25, "high": 1548.25, "low": 1547.25, "close": 1547.75, "volume": 933}, {"time": 1371376500, "open": 1547.75, "high": 1548.25, "low": 1547.75, "close": 1548.0, "volume": 121}, {"time": 1371376560, "open": 1547.75, "high": 1548.0, "low": 1547.75, "close": 1548.0, "volume": 7}, {"time": 1371376620, "open": 1547.75, "high": 1547.75, "low": 1547.75, "close": 1547.75, "volume": 33}, {"time": 1371376680, "open": 1547.75, "high": 1548.0, "low": 1547.75, "close": 1548.0, "volume": 39}, {"time": 1371376740, "open": 1547.75, "high": 1548.0, "low": 1547.75, "close": 1547.75, "volume": 72}, {"time": 1371376800, "open": 1547.75, "high": 1548.0, "low": 1547.5, "close": 1547.5, "volume": 187}, {"time": 1371376860, "open": 1547.5, "high": 1547.75, "low": 1547.25, "close": 1547.25, "volume": 362}, {"time": 1371376920, "open": 1547.5, "high": 1547.5, "low": 1547.0, "close": 1547.25, "volume": 204}, {"time": 1371376980, "open": 1547.25, "high": 1547.25, "low": 1547.0, "close": 1547.25, "volume": 108}, {"time": 1371377040, "open": 1547.25, "high": 1548.25, "low": 1547.25, "close": 1548.25, "volume": 389}, {"time": 1371377100, "open": 1548.5, "high": 1548.75, "low": 1548.5, "close": 1548.75, "volume": 619}, {"time": 1371377160, "open": 1548.75, "high": 1549.75, "low": 1548.75, "close": 1549.5, "volume": 675}, {"time": 1371377220, "open": 1549.25, "high": 1550.0, "low": 1549.25, "close": 1549.5, "volume": 500}, {"time": 1371377280, "open": 1549.75, "high": 1550.0, "low": 1549.25, "close": 1549.75, "volume": 1786}, {"time": 1371377340, "open": 1549.75, "high": 1550.0, "low": 1549.5, "close": 1549.5, "volume": 141}, {"time": 1371377400, "open": 1549.5, "high": 1549.5, "low": 1549.0, "close": 1549.25, "volume": 282}, {"time": 1371377460, "open": 1549.5, "high": 1549.75, "low": 1549.25, "close": 1549.5, "volume": 196}, {"time": 1371377520, "open": 1549.25, "high": 1549.5, "low": 1549.25, "close": 1549.5, "volume": 53}, {"time": 1371377580, "open": 1549.25, "high": 1549.25, "low": 1549.0, "close": 1549.0, "volume": 146}, {"time": 1371377640, "open": 1549.25, "high": 1549.5, "low": 1549.0, "close": 1549.0, "volume": 154}, {"time": 1371377700, "open": 1549.0, "high": 1549.5, "low": 1549.0, "close": 1549.25, "volume": 103}, {"time": 1371377760, "open": 1549.25, "high": 1549.5, "low": 1549.0, "close": 1549.25, "volume": 81}, {"time": 1371377820, "open": 1549.25, "high": 1549.5, "low": 1549.25, "close": 1549.5, "volume": 45}, {"time": 1371377880, "open": 1549.5, "high": 1549.5, "low": 1549.0, "close": 1549.0, "volume": 66}, {"time": 1371377940, "open": 1549.0, "high": 1549.25, "low": 1548.75, "close": 1549.0, "volume": 53}, {"time": 1371378000, "open": 1549.0, "high": 1549.25, "low": 1548.75, "close": 1549.0, "volume": 51}, {"time": 1371378060, "open": 1549.25, "high": 1549.25, "low": 1549.0, "close": 1549.0, "volume": 33}, {"time": 1371378120, "open": 1549.0, "high": 1549.25, "low": 1548.75, "close": 1548.75, "volume": 85}, {"time": 1371378180, "open": 1548.75, "high": 1549.25, "low": 1548.75, "close": 1549.25, "volume": 99}, {"time": 1371378240, "open": 1549.25, "high": 1549.5, "low": 1549.0, "close": 1549.25, "volume": 109}, {"time": 1371378300, "open": 1549.25, "high": 1549.5, "low": 1549.0, "close": 1549.25, "volume": 69}, {"time": 1371378360, "open": 1549.25, "high": 1549.25, "low": 1548.75, "close": 1548.75, "volume": 73}, {"time": 1371378420, "open": 1548.75, "high": 1549.0, "low": 1548.5, "close": 1548.5, "volume": 55}, {"time": 1371378480, "open": 1548.75, "high": 1548.75, "low": 1548.5, "close": 1548.75, "volume": 38}, {"time": 1371378540, "open": 1548.75, "high": 1548.75, "low": 1548.25, "close": 1548.25, "volume": 88}, {"time": 1371378600, "open": 1548.25, "high": 1548.5, "low": 1548.25, "close": 1548.5, "volume": 37}, {"time": 1371378660, "open": 1548.5, "high": 1548.75, "low": 1548.25, "close": 1548.25, "volume": 179}, {"time": 1371378720, "open": 1548.25, "high": 1548.5, "low": 1548.25, "close": 1548.5, "volume": 229}, {"time": 1371378780, "open": 1548.5, "high": 1548.75, "low": 1548.25, "close": 1548.25, "volume": 291}, {"time": 1371378840, "open": 1548.5, "high": 1548.75, "low": 1548.25, "close": 1548.5, "volume": 160}, {"time": 1371378900, "open": 1548.25, "high": 1548.5, "low": 1548.25, "close": 1548.25, "volume": 69}, {"time": 1371378960, "open": 1548.5, "high": 1549.0, "low": 1548.25, "close": 1549.0, "volume": 165}, {"time": 1371379020, "open": 1549.0, "high": 1549.25, "low": 1548.75, "close": 1549.25, "volume": 56}, {"time": 1371379080, "open": 1549.0, "high": 1549.25, "low": 1548.75, "close": 1549.0, "volume": 150}, {"time": 1371379140, "open": 1549.25, "high": 1549.25, "low": 1548.75, "close": 1549.0, "volume": 80}, {"time": 1371379200, "open": 1548.75, "high": 1549.0, "low": 1548.5, "close": 1549.0, "volume": 143}, {"time": 1371379260, "open": 1549.0, "high": 1549.25, "low": 1548.75, "close": 1549.25, "volume": 72}, {"time": 1371379320, "open": 1549.0, "high": 1549.25, "low": 1549.0, "close": 1549.25, "volume": 99}, {"time": 1371379380, "open": 1549.25, "high": 1549.25, "low": 1549.0, "close": 1549.25, "volume": 18}, {"time": 1371379440, "open": 1549.25, "high": 1549.25, "low": 1549.0, "close": 1549.0, "volume": 26}, {"time": 1371379500, "open": 1549.0, "high": 1549.25, "low": 1548.75, "close": 1548.75, "volume": 130}, {"time": 1371379560, "open": 1549.0, "high": 1549.0, "low": 1548.75, "close": 1549.0, "volume": 79}, {"time": 1371379620, "open": 1549.0, "high": 1549.0, "low": 1548.75, "close": 1548.75, "volume": 131}, {"time": 1371379680, "open": 1548.5, "high": 1548.75, "low": 1548.5, "close": 1548.5, "volume": 65}, {"time": 1371379740, "open": 1548.5, "high": 1548.75, "low": 1548.5, "close": 1548.75, "volume": 26}, {"time": 1371379800, "open": 1548.75, "high": 1548.75, "low": 1548.5, "close": 1548.75, "volume": 49}, {"time": 1371379860, "open": 1548.75, "high": 1548.75, "low": 1548.5, "close": 1548.5, "volume": 116}, {"time": 1371379920, "open": 1548.25, "high": 1548.5, "low": 1548.25, "close": 1548.25, "volume": 109}, {"time": 1371379980, "open": 1548.5, "high": 1549.0, "low": 1548.25, "close": 1549.0, "volume": 102}, {"time": 1371380040, "open": 1548.75, "high": 1549.0, "low": 1548.75, "close": 1548.75, "volume": 31}, {"time": 1371380100, "open": 1549.0, "high": 1549.25, "low": 1548.75, "close": 1549.0, "volume": 66}, {"time": 1371380160, "open": 1548.75, "high": 1549.0, "low": 1548.75, "close": 1549.0, "volume": 14}, {"time": 1371380220, "open": 1548.75, "high": 1548.75, "low": 1548.5, "close": 1548.5, "volume": 103}, {"time": 1371380280, "open": 1548.5, "high": 1548.5, "low": 1548.5, "close": 1548.5, "volume": 17}, {"time": 1371380340, "open": 1548.5, "high": 1548.75, "low": 1548.5, "close": 1548.5, "volume": 28}, {"time": 1371380400, "open": 1548.75, "high": 1549.0, "low": 1548.75, "close": 1548.75, "volume": 121}, {"time": 1371380460, "open": 1548.75, "high": 1548.75, "low": 1548.5, "close": 1548.75, "volume": 118}, {"time": 1371380520, "open": 1548.75, "high": 1549.0, "low": 1548.5, "close": 1548.5, "volume": 45}, {"time": 1371380580, "open": 1548.75, "high": 1549.0, "low": 1548.5, "close": 1549.0, "volume": 88}, {"time": 1371380640, "open": 1548.75, "high": 1549.0, "low": 1548.75, "close": 1549.0, "volume": 76}, {"time": 1371380700, "open": 1549.25, "high": 1549.25, "low": 1549.0, "close": 1549.25, "volume": 65}, {"time": 1371380760, "open": 1549.0, "high": 1549.25, "low": 1549.0, "close": 1549.25, "volume": 90}, {"time": 1371380820, "open": 1549.5, "high": 1549.75, "low": 1549.5, "close": 1549.5, "volume": 425}, {"time": 1371380880, "open": 1549.5, "high": 1549.75, "low": 1549.25, "close": 1549.5, "volume": 277}, {"time": 1371380940, "open": 1549.5, "high": 1549.75, "low": 1549.25, "close": 1549.75, "volume": 132}, {"time": 1371381000, "open": 1549.5, "high": 1549.75, "low": 1549.5, "close": 1549.75, "volume": 84}, {"time": 1371381060, "open": 1549.5, "high": 1549.75, "low": 1549.5, "close": 1549.5, "volume": 222}, {"time": 1371381120, "open": 1549.75, "high": 1549.75, "low": 1549.5, "close": 1549.5, "volume": 64}, {"time": 1371381180, "open": 1549.5, "high": 1549.5, "low": 1549.25, "close": 1549.25, "volume": 112}, {"time": 1371381240, "open": 1549.25, "high": 1549.5, "low": 1549.25, "close": 1549.5, "volume": 24}, {"time": 1371381300, "open": 1549.25, "high": 1549.75, "low": 1549.25, "close": 1549.5, "volume": 81}, {"time": 1371381360, "open": 1549.5, "high": 1549.75, "low": 1549.5, "close": 1549.75, "volume": 31}, {"time": 1371381420, "open": 1549.5, "high": 1549.75, "low": 1549.5, "close": 1549.5, "volume": 36}, {"time": 1371381480, "open": 1549.75, "high": 1549.75, "low": 1549.5, "close": 1549.75, "volume": 40}, {"time": 1371381540, "open": 1549.5, "high": 1549.5, "low": 1549.25, "close": 1549.25, "volume": 91}, {"time": 1371381600, "open": 1549.25, "high": 1549.75, "low": 1549.25, "close": 1549.75, "volume": 82}, {"time": 1371381660, "open": 1549.5, "high": 1549.75, "low": 1549.5, "close": 1549.5, "volume": 60}, {"time": 1371381720, "open": 1549.75, "high": 1549.75, "low": 1549.5, "close": 1549.5, "volume": 32}, {"time": 1371381780, "open": 1549.5, "high": 1549.75, "low": 1549.5, "close": 1549.5, "volume": 49}, {"time": 1371381840, "open": 1549.5, "high": 1550.0, "low": 1549.5, "close": 1549.75, "volume": 224}, {"time": 1371381900, "open": 1549.75, "high": 1549.75, "low": 1549.5, "close": 1549.5, "volume": 28}, {"time": 1371381960, "open": 1549.75, "high": 1550.25, "low": 1549.75, "close": 1550.0, "volume": 225}, {"time": 1371382020, "open": 1550.25, "high": 1550.25, "low": 1550.0, "close": 1550.0, "volume": 69}, {"time": 1371382080, "open": 1550.0, "high": 1550.25, "low": 1549.75, "close": 1550.0, "volume": 63}, {"time": 1371382140, "open": 1550.0, "high": 1550.0, "low": 1549.75, "close": 1549.75, "volume": 134}, {"time": 1371382200, "open": 1549.75, "high": 1550.25, "low": 1549.75, "close": 1550.0, "volume": 256}, {"time": 1371382260, "open": 1550.0, "high": 1550.25, "low": 1550.0, "close": 1550.25, "volume": 16}, {"time": 1371382320, "open": 1550.0, "high": 1550.0, "low": 1550.0, "close": 1550.0, "volume": 20}, {"time": 1371382380, "open": 1550.25, "high": 1550.5, "low": 1550.0, "close": 1550.25, "volume": 237}, {"time": 1371382440, "open": 1550.5, "high": 1550.5, "low": 1550.25, "close": 1550.25, "volume": 63}, {"time": 1371382500, "open": 1550.25, "high": 1550.25, "low": 1549.75, "close": 1549.75, "volume": 128}, {"time": 1371382560, "open": 1549.75, "high": 1550.0, "low": 1549.5, "close": 1549.5, "volume": 152}, {"time": 1371382620, "open": 1549.75, "high": 1549.75, "low": 1549.5, "close": 1549.5, "volume": 158}, {"time": 1371382680, "open": 1549.5, "high": 1549.75, "low": 1549.25, "close": 1549.5, "volume": 195}, {"time": 1371382740, "open": 1549.5, "high": 1550.0, "low": 1549.5, "close": 1550.0, "volume": 122}, {"time": 1371382800, "open": 1549.75, "high": 1550.0, "low": 1549.75, "close": 1550.0, "volume": 52}, {"time": 1371382860, "open": 1550.25, "high": 1550.25, "low": 1550.0, "close": 1550.0, "volume": 22}, {"time": 1371382920, "open": 1550.0, "high": 1550.0, "low": 1549.75, "close": 1549.75, "volume": 237}, {"time": 1371382980, "open": 1549.75, "high": 1549.75, "low": 1549.75, "close": 1549.75, "volume": 129}, {"time": 1371383040, "open": 1549.75, "high": 1550.0, "low": 1549.75, "close": 1550.0, "volume": 21}, {"time": 1371383100, "open": 1549.75, "high": 1550.0, "low": 1549.75, "close": 1550.0, "volume": 131}, {"time": 1371383160, "open": 1550.0, "high": 1550.25, "low": 1550.0, "close": 1550.25, "volume": 200}, {"time": 1371383220, "open": 1550.0, "high": 1550.5, "low": 1550.0, "close": 1550.0, "volume": 92}, {"time": 1371383280, "open": 1550.0, "high": 1550.25, "low": 1550.0, "close": 1550.0, "volume": 19}, {"time": 1371383340, "open": 1550.0, "high": 1550.0, "low": 1550.0, "close": 1550.0, "volume": 16}, {"time": 1371383400, "open": 1550.0, "high": 1550.5, "low": 1550.0, "close": 1550.25, "volume": 132}, {"time": 1371383460, "open": 1550.5, "high": 1551.0, "low": 1550.25, "close": 1551.0, "volume": 668}, {"time": 1371383520, "open": 1551.0, "high": 1551.0, "low": 1550.75, "close": 1551.0, "volume": 85}, {"time": 1371383580, "open": 1551.0, "high": 1551.0, "low": 1550.75, "close": 1551.0, "volume": 29}, {"time": 1371383640, "open": 1550.75, "high": 1551.0, "low": 1550.75, "close": 1550.75, "volume": 40}, {"time": 1371383700, "open": 1550.75, "high": 1550.75, "low": 1550.75, "close": 1550.75, "volume": 48}, {"time": 1371383760, "open": 1550.5, "high": 1550.75, "low": 1550.5, "close": 1550.75, "volume": 74}, {"time": 1371383820, "open": 1551.0, "high": 1551.0, "low": 1550.75, "close": 1550.75, "volume": 105}, {"time": 1371383880, "open": 1550.75, "high": 1550.75, "low": 1550.5, "close": 1550.75, "volume": 116}, {"time": 1371383940, "open": 1550.75, "high": 1550.75, "low": 1550.5, "close": 1550.5, "volume": 37}, {"time": 1371384000, "open": 1550.5, "high": 1551.0, "low": 1550.5, "close": 1550.75, "volume": 84}, {"time": 1371384060, "open": 1551.0, "high": 1551.0, "low": 1550.75, "close": 1551.0, "volume": 18}, {"time": 1371384120, "open": 1551.0, "high": 1551.0, "low": 1550.75, "close": 1550.75, "volume": 26}, {"time": 1371384180, "open": 1551.0, "high": 1551.0, "low": 1550.75, "close": 1551.0, "volume": 17}, {"time": 1371384240, "open": 1550.75, "high": 1551.25, "low": 1550.75, "close": 1550.75, "volume": 111}, {"time": 1371384300, "open": 1550.75, "high": 1551.0, "low": 1550.5, "close": 1550.5, "volume": 38}, {"time": 1371384360, "open": 1550.5, "high": 1550.5, "low": 1550.25, "close": 1550.5, "volume": 57}, {"time": 1371384420, "open": 1550.25, "high": 1550.5, "low": 1550.25, "close": 1550.25, "volume": 107}, {"time": 1371384480, "open": 1550.5, "high": 1550.5, "low": 1550.25, "close": 1550.25, "volume": 281}, {"time": 1371384540, "open": 1550.25, "high": 1550.25, "low": 1550.25, "close": 1550.25, "volume": 17}, {"time": 1371384600, "open": 1550.25, "high": 1550.5, "low": 1550.25, "close": 1550.5, "volume": 19}, {"time": 1371384660, "open": 1550.25, "high": 1550.5, "low": 1550.25, "close": 1550.25, "volume": 57}, {"time": 1371384720, "open": 1550.25, "high": 1550.5, "low": 1550.25, "close": 1550.25, "volume": 181}, {"time": 1371384780, "open": 1550.25, "high": 1550.5, "low": 1550.25, "close": 1550.25, "volume": 158}, {"time": 1371384840, "open": 1550.25, "high": 1550.5, "low": 1550.25, "close": 1550.25, "volume": 19}, {"time": 1371384900, "open": 1550.25, "high": 1550.25, "low": 1550.25, "close": 1550.25, "volume": 19}, {"time": 1371384960, "open": 1550.25, "high": 1550.5, "low": 1550.25, "close": 1550.5, "volume": 61}, {"time": 1371385020, "open": 1550.75, "high": 1550.75, "low": 1550.25, "close": 1550.25, "volume": 42}, {"time": 1371385080, "open": 1550.25, "high": 1550.25, "low": 1549.75, "close": 1549.75, "volume": 200}, {"time": 1371385140, "open": 1549.75, "high": 1550.25, "low": 1549.75, "close": 1550.25, "volume": 92}, {"time": 1371385200, "open": 1550.0, "high": 1550.25, "low": 1550.0, "close": 1550.25, "volume": 28}, {"time": 1371385260, "open": 1550.0, "high": 1550.0, "low": 1550.0, "close": 1550.0, "volume": 14}, {"time": 1371385320, "open": 1550.0, "high": 1550.5, "low": 1550.0, "close": 1550.25, "volume": 51}, {"time": 1371385380, "open": 1550.25, "high": 1550.5, "low": 1550.25, "close": 1550.5, "volume": 18}, {"time": 1371385440, "open": 1550.25, "high": 1550.25, "low": 1550.25, "close": 1550.25, "volume": 19}, {"time": 1371385500, "open": 1550.25, "high": 1550.25, "low": 1550.0, "close": 1550.0, "volume": 18}, {"time": 1371385560, "open": 1550.0, "high": 1550.0, "low": 1550.0, "close": 1550.0, "volume": 20}, {"time": 1371385620, "open": 1550.0, "high": 1550.0, "low": 1550.0, "close": 1550.0, "volume": 13}, {"time": 1371385680, "open": 1550.25, "high": 1550.25, "low": 1550.25, "close": 1550.25, "volume": 56}, {"time": 1371385740, "open": 1550.25, "high": 1550.5, "low": 1550.25, "close": 1550.25, "volume": 109}, {"time": 1371385800, "open": 1550.25, "high": 1550.5, "low": 1550.25, "close": 1550.25, "volume": 13}, {"time": 1371385860, "open": 1550.25, "high": 1550.25, "low": 1550.25, "close": 1550.25, "volume": 2}, {"time": 1371385920, "open": 1550.5, "high": 1550.75, "low": 1550.5, "close": 1550.75, "volume": 23}, {"time": 1371385980, "open": 1550.5, "high": 1550.5, "low": 1550.25, "close": 1550.25, "volume": 34}, {"time": 1371386040, "open": 1550.5, "high": 1550.5, "low": 1549.75, "close": 1549.75, "volume": 200}, {"time": 1371386100, "open": 1549.5, "high": 1550.0, "low": 1549.5, "close": 1550.0, "volume": 46}, {"time": 1371386160, "open": 1549.75, "high": 1549.75, "low": 1549.75, "close": 1549.75, "volume": 75}, {"time": 1371386220, "open": 1549.75, "high": 1550.0, "low": 1549.75, "close": 1550.0, "volume": 4}, {"time": 1371386280, "open": 1550.0, "high": 1550.25, "low": 1550.0, "close": 1550.25, "volume": 32}, {"time": 1371386340, "open": 1550.25, "high": 1550.25, "low": 1550.25, "close": 1550.25, "volume": 11}, {"time": 1371386400, "open": 1550.0, "high": 1550.25, "low": 1550.0, "close": 1550.0, "volume": 8}, {"time": 1371386520, "open": 1550.0, "high": 1550.25, "low": 1550.0, "close": 1550.25, "volume": 3}, {"time": 1371386580, "open": 1550.25, "high": 1550.25, "low": 1550.25, "close": 1550.25, "volume": 34}, {"time": 1371386640, "open": 1550.5, "high": 1550.5, "low": 1550.25, "close": 1550.5, "volume": 83}, {"time": 1371386700, "open": 1550.5, "high": 1550.75, "low": 1550.5, "close": 1550.75, "volume": 41}, {"time": 1371386760, "open": 1550.75, "high": 1550.75, "low": 1550.5, "close": 1550.75, "volume": 5}, {"time": 1371386820, "open": 1550.75, "high": 1550.75, "low": 1550.5, "close": 1550.75, "volume": 73}, {"time": 1371386880, "open": 1550.75, "high": 1550.75, "low": 1550.75, "close": 1550.75, "volume": 12}, {"time": 1371386940, "open": 1550.75, "high": 1551.0, "low": 1550.75, "close": 1550.75, "volume": 32}, {"time": 1371387000, "open": 1550.5, "high": 1550.5, "low": 1550.5, "close": 1550.5, "volume": 8}, {"time": 1371387060, "open": 1550.5, "high": 1550.5, "low": 1550.5, "close": 1550.5, "volume": 1}, {"time": 1371387120, "open": 1550.75, "high": 1550.75, "low": 1550.75, "close": 1550.75, "volume": 17}, {"time": 1371387180, "open": 1550.75, "high": 1550.75, "low": 1550.75, "close": 1550.75, "volume": 5}, {"time": 1371387240, "open": 1550.5, "high": 1550.5, "low": 1550.5, "close": 1550.5, "volume": 2}, {"time": 1371387360, "open": 1550.5, "high": 1550.5, "low": 1550.5, "close": 1550.5, "volume": 30}, {"time": 1371387420, "open": 1550.5, "high": 1550.5, "low": 1550.25, "close": 1550.5, "volume": 9}, {"time": 1371387480, "open": 1550.5, "high": 1550.5, "low": 1550.5, "close": 1550.5, "volume": 6}, {"time": 1371387540, "open": 1550.5, "high": 1550.5, "low": 1550.5, "close": 1550.5, "volume": 74}, {"time": 1371387600, "open": 1550.5, "high": 1550.5, "low": 1550.25, "close": 1550.5, "volume": 9}, {"time": 1371387660, "open": 1550.25, "high": 1550.5, "low": 1550.25, "close": 1550.5, "volume": 18}, {"time": 1371387720, "open": 1550.75, "high": 1550.75, "low": 1550.75, "close": 1550.75, "volume": 1}, {"time": 1371387780, "open": 1550.5, "high": 1550.75, "low": 1550.5, "close": 1550.5, "volume": 20}, {"time": 1371387840, "open": 1550.5, "high": 1550.5, "low": 1550.5, "close": 1550.5, "volume": 7}, {"time": 1371388020, "open": 1550.5, "high": 1550.5, "low": 1550.25, "close": 1550.25, "volume": 29}, {"time": 1371388080, "open": 1550.25, "high": 1550.5, "low": 1550.25, "close": 1550.5, "volume": 27}, {"time": 1371388140, "open": 1550.25, "high": 1550.25, "low": 1550.25, "close": 1550.25, "volume": 10}, {"time": 1371388200, "open": 1550.25, "high": 1550.25, "low": 1550.25, "close": 1550.25, "volume": 1}, {"time": 1371388260, "open": 1550.5, "high": 1550.5, "low": 1550.5, "close": 1550.5, "volume": 82}, {"time": 1371388320, "open": 1550.5, "high": 1550.75, "low": 1550.5, "close": 1550.75, "volume": 23}, {"time": 1371388380, "open": 1550.75, "high": 1550.75, "low": 1550.5, "close": 1550.75, "volume": 20}, {"time": 1371388440, "open": 1550.5, "high": 1550.75, "low": 1550.5, "close": 1550.75, "volume": 12}, {"time": 1371388500, "open": 1550.75, "high": 1550.75, "low": 1550.5, "close": 1550.5, "volume": 4}, {"time": 1371388560, "open": 1550.5, "high": 1550.75, "low": 1550.5, "close": 1550.75, "volume": 4}, {"time": 1371388620, "open": 1550.5, "high": 1550.75, "low": 1550.5, "close": 1550.75, "volume": 8}, {"time": 1371388680, "open": 1550.75, "high": 1550.75, "low": 1550.75, "close": 1550.75, "volume": 9}, {"time": 1371388740, "open": 1550.5, "high": 1550.75, "low": 1550.5, "close": 1550.75, "volume": 76}, {"time": 1371388800, "open": 1550.75, "high": 1550.75, "low": 1550.5, "close": 1550.5, "volume": 142}, {"time": 1371388860, "open": 1550.5, "high": 1550.75, "low": 1550.5, "close": 1550.5, "volume": 24}, {"time": 1371388980, "open": 1550.5, "high": 1550.5, "low": 1550.5, "close": 1550.5, "volume": 17}, {"time": 1371389040, "open": 1550.75, "high": 1550.75, "low": 1550.5, "close": 1550.5, "volume": 16}, {"time": 1371389100, "open": 1550.5, "high": 1550.5, "low": 1550.5, "close": 1550.5, "volume": 6}, {"time": 1371389220, "open": 1550.75, "high": 1551.0, "low": 1550.75, "close": 1550.75, "volume": 53}, {"time": 1371389280, "open": 1550.75, "high": 1550.75, "low": 1550.75, "close": 1550.75, "volume": 94}, {"time": 1371389340, "open": 1550.75, "high": 1550.75, "low": 1550.75, "close": 1550.75, "volume": 133}, {"time": 1371389400, "open": 1551.0, "high": 1551.0, "low": 1550.75, "close": 1551.0, "volume": 106}, {"time": 1371389460, "open": 1551.25, "high": 1551.25, "low": 1551.0, "close": 1551.0, "volume": 93}, {"time": 1371389520, "open": 1551.0, "high": 1551.0, "low": 1551.0, "close": 1551.0, "volume": 111}, {"time": 1371389580, "open": 1551.0, "high": 1551.0, "low": 1551.0, "close": 1551.0, "volume": 8}, {"time": 1371389640, "open": 1551.0, "high": 1551.0, "low": 1550.75, "close": 1550.75, "volume": 8}, {"time": 1371389700, "open": 1550.75, "high": 1551.0, "low": 1550.75, "close": 1551.0, "volume": 100}, {"time": 1371389760, "open": 1551.0, "high": 1551.0, "low": 1551.0, "close": 1551.0, "volume": 14}, {"time": 1371389820, "open": 1551.0, "high": 1551.0, "low": 1551.0, "close": 1551.0, "volume": 3}, {"time": 1371389880, "open": 1551.0, "high": 1551.0, "low": 1551.0, "close": 1551.0, "volume": 20}, {"time": 1371389940, "open": 1551.0, "high": 1551.25, "low": 1551.0, "close": 1551.0, "volume": 6}, {"time": 1371390000, "open": 1551.0, "high": 1551.0, "low": 1550.75, "close": 1550.75, "volume": 122}, {"time": 1371390060, "open": 1550.75, "high": 1550.75, "low": 1550.75, "close": 1550.75, "volume": 10}, {"time": 1371390120, "open": 1550.5, "high": 1550.75, "low": 1550.5, "close": 1550.75, "volume": 6}, {"time": 1371390240, "open": 1550.5, "high": 1550.5, "low": 1550.5, "close": 1550.5, "volume": 139}, {"time": 1371390300, "open": 1550.5, "high": 1550.5, "low": 1549.75, "close": 1549.75, "volume": 186}, {"time": 1371390360, "open": 1549.75, "high": 1550.0, "low": 1549.75, "close": 1549.75, "volume": 172}, {"time": 1371390420, "open": 1549.75, "high": 1550.25, "low": 1549.5, "close": 1549.5, "volume": 487}, {"time": 1371390480, "open": 1549.5, "high": 1549.5, "low": 1549.5, "close": 1549.5, "volume": 89}, {"time": 1371390540, "open": 1549.5, "high": 1549.5, "low": 1549.0, "close": 1549.25, "volume": 509}, {"time": 1371390600, "open": 1549.25, "high": 1549.75, "low": 1549.25, "close": 1549.75, "volume": 35}, {"time": 1371390660, "open": 1549.75, "high": 1549.75, "low": 1549.75, "close": 1549.75, "volume": 20}, {"time": 1371390720, "open": 1550.0, "high": 1550.0, "low": 1549.75, "close": 1549.75, "volume": 15}, {"time": 1371390780, "open": 1550.0, "high": 1550.0, "low": 1550.0, "close": 1550.0, "volume": 11}, {"time": 1371390840, "open": 1550.0, "high": 1550.25, "low": 1550.0, "close": 1550.25, "volume": 32}, {"time": 1371390900, "open": 1550.25, "high": 1550.25, "low": 1550.0, "close": 1550.25, "volume": 152}, {"time": 1371390960, "open": 1550.25, "high": 1550.75, "low": 1550.25, "close": 1550.5, "volume": 94}, {"time": 1371391020, "open": 1550.75, "high": 1550.75, "low": 1550.5, "close": 1550.5, "volume": 12}, {"time": 1371391080, "open": 1550.75, "high": 1550.75, "low": 1550.75, "close": 1550.75, "volume": 66}, {"time": 1371391140, "open": 1551.0, "high": 1551.0, "low": 1551.0, "close": 1551.0, "volume": 34}]